{"battles":27416,"avg":1,"pokemon":[{"name":"Deoxys-Attack","usage":18.36519,"raw":10070,"rawp":18.365,"real":364,"realp":3.983},{"name":"Arceus","usage":16.55603,"raw":9078,"rawp":16.556,"real":296,"realp":3.239},{"name":"Deoxys-Speed","usage":12.37963,"raw":6788,"rawp":12.38,"real":74,"realp":0.81},{"name":"Shuckle","usage":11.3328,"raw":6214,"rawp":11.333,"real":223,"realp":2.44},{"name":"Giratina","usage":10.98993,"raw":6026,"rawp":10.99,"real":560,"realp":6.127},{"name":"Lugia","usage":9.61118,"raw":5270,"rawp":9.611,"real":215,"realp":2.352},{"name":"Sableye","usage":9.51452,"raw":5217,"rawp":9.515,"real":2623,"realp":28.699},{"name":"Greninja","usage":8.27072,"raw":4535,"rawp":8.271,"real":412,"realp":4.508},{"name":"Kyurem-Black","usage":7.9242,"raw":4345,"rawp":7.924,"real":295,"realp":3.228},{"name":"Chansey","usage":7.80384,"raw":4279,"rawp":7.804,"real":1076,"realp":11.773},{"name":"Xerneas","usage":7.56857,"raw":4150,"rawp":7.569,"real":317,"realp":3.468},{"name":"Lunala","usage":7.55763,"raw":4144,"rawp":7.558,"real":527,"realp":5.766},{"name":"Clefable","usage":7.26401,"raw":3983,"rawp":7.264,"real":903,"realp":9.88},{"name":"Rayquaza-Mega","usage":7.06339,"raw":3873,"rawp":7.063,"real":375,"realp":4.103},{"name":"Delcatty","usage":6.98862,"raw":3832,"rawp":6.989,"real":68,"realp":0.744},{"name":"Kyurem-White","usage":6.89926,"raw":3783,"rawp":6.899,"real":150,"realp":1.641},{"name":"Blissey","usage":6.52721,"raw":3579,"rawp":6.527,"real":734,"realp":8.031},{"name":"Marshadow","usage":6.20988,"raw":3405,"rawp":6.21,"real":755,"realp":8.261},{"name":"Slaking","usage":6.0731,"raw":3330,"rawp":6.073,"real":267,"realp":2.921},{"name":"Rayquaza","usage":5.87066,"raw":3219,"rawp":5.871,"real":131,"realp":1.433},{"name":"Persian-Alola","usage":5.76123,"raw":3159,"rawp":5.761,"real":86,"realp":0.941},{"name":"Mewtwo","usage":5.57886,"raw":3059,"rawp":5.579,"real":128,"realp":1.4},{"name":"Blacephalon","usage":5.32353,"raw":2919,"rawp":5.324,"real":112,"realp":1.225},{"name":"Kartana","usage":5.31806,"raw":2916,"rawp":5.318,"real":223,"realp":2.44},{"name":"Mew","usage":5.18858,"raw":2845,"rawp":5.189,"real":80,"realp":0.875},{"name":"Reshiram","usage":5.17763,"raw":2839,"rawp":5.178,"real":1082,"realp":11.839},{"name":"Victini","usage":5.13933,"raw":2818,"rawp":5.139,"real":130,"realp":1.422},{"name":"Aegislash","usage":4.94602,"raw":2712,"rawp":4.946,"real":1631,"realp":17.845},{"name":"Ho-Oh","usage":4.86577,"raw":2668,"rawp":4.866,"real":839,"realp":9.18},{"name":"Skitty","usage":4.58127,"raw":2512,"rawp":4.581,"real":79,"realp":0.864},{"name":"Dragonite","usage":4.5375,"raw":2488,"rawp":4.537,"real":78,"realp":0.853},{"name":"Celesteela","usage":4.52655,"raw":2482,"rawp":4.527,"real":517,"realp":5.657},{"name":"Heatran","usage":4.20375,"raw":2305,"rawp":4.204,"real":603,"realp":6.598},{"name":"Groudon","usage":4.01043,"raw":2199,"rawp":4.01,"real":893,"realp":9.771},{"name":"Swoobat","usage":3.87365,"raw":2124,"rawp":3.874,"real":72,"realp":0.788},{"name":"Zekrom","usage":3.70951,"raw":2034,"rawp":3.71,"real":421,"realp":4.606},{"name":"Yveltal","usage":3.61833,"raw":1984,"rawp":3.618,"real":314,"realp":3.436},{"name":"Spiritomb","usage":3.60191,"raw":1975,"rawp":3.602,"real":1581,"realp":17.298},{"name":"Mimikyu","usage":3.59826,"raw":1973,"rawp":3.598,"real":773,"realp":8.458},{"name":"Regigigas","usage":3.55085,"raw":1947,"rawp":3.551,"real":139,"realp":1.521},{"name":"Alakazam","usage":3.46695,"raw":1901,"rawp":3.467,"real":62,"realp":0.678},{"name":"Tapu Lele","usage":3.39583,"raw":1862,"rawp":3.396,"real":162,"realp":1.772},{"name":"Ferrothorn","usage":3.36118,"raw":1843,"rawp":3.361,"real":453,"realp":4.956},{"name":"Kyogre","usage":3.32105,"raw":1821,"rawp":3.321,"real":169,"realp":1.849},{"name":"Araquanid","usage":3.31376,"raw":1817,"rawp":3.314,"real":351,"realp":3.84},{"name":"Murkrow","usage":3.21892,"raw":1765,"rawp":3.219,"real":37,"realp":0.405},{"name":"Serperior","usage":3.17333,"raw":1740,"rawp":3.173,"real":37,"realp":0.405},{"name":"Espeon","usage":3.12956,"raw":1716,"rawp":3.13,"real":31,"realp":0.339},{"name":"Pheromosa","usage":3.04749,"raw":1671,"rawp":3.047,"real":63,"realp":0.689},{"name":"Muk-Alola","usage":2.9253,"raw":1604,"rawp":2.925,"real":1155,"realp":12.637},{"name":"Skarmory","usage":2.83958,"raw":1557,"rawp":2.84,"real":448,"realp":4.902},{"name":"Gengar","usage":2.75022,"raw":1508,"rawp":2.75,"real":614,"realp":6.718},{"name":"Dialga","usage":2.68092,"raw":1470,"rawp":2.681,"real":692,"realp":7.571},{"name":"Golem-Alola","usage":2.6718,"raw":1465,"rawp":2.672,"real":125,"realp":1.368},{"name":"Sylveon","usage":2.62803,"raw":1441,"rawp":2.628,"real":81,"realp":0.886},{"name":"Jirachi","usage":2.60432,"raw":1428,"rawp":2.604,"real":206,"realp":2.254},{"name":"Magearna","usage":2.5642,"raw":1406,"rawp":2.564,"real":809,"realp":8.852},{"name":"Aurorus","usage":2.53684,"raw":1391,"rawp":2.537,"real":82,"realp":0.897},{"name":"Palkia","usage":2.50219,"raw":1372,"rawp":2.502,"real":537,"realp":5.875},{"name":"Deoxys-Defense","usage":2.47118,"raw":1355,"rawp":2.471,"real":22,"realp":0.241},{"name":"Blaziken","usage":2.4183,"raw":1326,"rawp":2.418,"real":161,"realp":1.762},{"name":"Magikarp","usage":2.34899,"raw":1288,"rawp":2.349,"real":418,"realp":4.573},{"name":"Mawile","usage":2.31069,"raw":1267,"rawp":2.311,"real":424,"realp":4.639},{"name":"Lucario","usage":2.26145,"raw":1240,"rawp":2.261,"real":105,"realp":1.149},{"name":"Zeraora","usage":2.23957,"raw":1228,"rawp":2.24,"real":176,"realp":1.926},{"name":"Solgaleo","usage":2.2341,"raw":1225,"rawp":2.234,"real":276,"realp":3.02},{"name":"Porygon-Z","usage":2.12285,"raw":1164,"rawp":2.123,"real":111,"realp":1.214},{"name":"Comfey","usage":2.11373,"raw":1159,"rawp":2.114,"real":101,"realp":1.105},{"name":"Zygarde","usage":2.11008,"raw":1157,"rawp":2.11,"real":82,"realp":0.897},{"name":"Togedemaru","usage":2.10461,"raw":1154,"rawp":2.105,"real":112,"realp":1.225},{"name":"Heliolisk","usage":2.06814,"raw":1134,"rawp":2.068,"real":51,"realp":0.558},{"name":"Gliscor","usage":2.06631,"raw":1133,"rawp":2.066,"real":70,"realp":0.766},{"name":"Klefki","usage":2.06631,"raw":1133,"rawp":2.066,"real":606,"realp":6.63},{"name":"Necrozma-Dusk-Mane","usage":2.05902,"raw":1129,"rawp":2.059,"real":128,"realp":1.4},{"name":"Landorus-Therian","usage":2.04078,"raw":1119,"rawp":2.041,"real":115,"realp":1.258},{"name":"Genesect","usage":2.04078,"raw":1119,"rawp":2.041,"real":308,"realp":3.37},{"name":"Doublade","usage":2.02619,"raw":1111,"rawp":2.026,"real":718,"realp":7.856},{"name":"Excadrill","usage":1.91494,"raw":1050,"rawp":1.915,"real":101,"realp":1.105},{"name":"Toxapex","usage":1.87664,"raw":1029,"rawp":1.877,"real":194,"realp":2.123},{"name":"Scizor","usage":1.85658,"raw":1018,"rawp":1.857,"real":681,"realp":7.451},{"name":"Xatu","usage":1.79822,"raw":986,"rawp":1.798,"real":16,"realp":0.175},{"name":"Arcanine","usage":1.73256,"raw":950,"rawp":1.733,"real":17,"realp":0.186},{"name":"Pikachu","usage":1.69791,"raw":931,"rawp":1.698,"real":317,"realp":3.468},{"name":"Togekiss","usage":1.68332,"raw":923,"rawp":1.683,"real":82,"realp":0.897},{"name":"Bidoof","usage":1.66144,"raw":911,"rawp":1.661,"real":209,"realp":2.287},{"name":"Riolu","usage":1.62314,"raw":890,"rawp":1.623,"real":41,"realp":0.449},{"name":"Salazzle","usage":1.60308,"raw":879,"rawp":1.603,"real":108,"realp":1.182},{"name":"Malamar","usage":1.54837,"raw":849,"rawp":1.548,"real":101,"realp":1.105},{"name":"Whimsicott","usage":1.52466,"raw":836,"rawp":1.525,"real":20,"realp":0.219},{"name":"Marowak-Alola","usage":1.52283,"raw":835,"rawp":1.523,"real":330,"realp":3.611},{"name":"Magnezone","usage":1.51736,"raw":832,"rawp":1.517,"real":283,"realp":3.096},{"name":"Stakataka","usage":1.51554,"raw":831,"rawp":1.516,"real":71,"realp":0.777},{"name":"Pangoro","usage":1.51189,"raw":829,"rawp":1.512,"real":293,"realp":3.206},{"name":"Gastly","usage":1.49001,"raw":817,"rawp":1.49,"real":437,"realp":4.781},{"name":"Celebi","usage":1.48089,"raw":812,"rawp":1.481,"real":20,"realp":0.219},{"name":"Nidoking","usage":1.47906,"raw":811,"rawp":1.479,"real":62,"realp":0.678},{"name":"Necrozma-Dawn-Wings","usage":1.41341,"raw":775,"rawp":1.413,"real":149,"realp":1.63},{"name":"Kecleon","usage":1.39882,"raw":767,"rawp":1.399,"real":86,"realp":0.941},{"name":"Komala","usage":1.3897,"raw":762,"rawp":1.39,"real":14,"realp":0.153},{"name":"Honedge","usage":1.38058,"raw":757,"rawp":1.381,"real":648,"realp":7.09},{"name":"Wooper","usage":1.37693,"raw":755,"rawp":1.377,"real":333,"realp":3.643},{"name":"Volcanion","usage":1.35505,"raw":743,"rawp":1.355,"real":201,"realp":2.199},{"name":"Durant","usage":1.33316,"raw":731,"rawp":1.333,"real":66,"realp":0.722},{"name":"Furfrou","usage":1.32222,"raw":725,"rawp":1.322,"real":6,"realp":0.066},{"name":"Pyukumuku","usage":1.30581,"raw":716,"rawp":1.306,"real":54,"realp":0.591},{"name":"Aggron","usage":1.29122,"raw":708,"rawp":1.291,"real":38,"realp":0.416},{"name":"Talonflame","usage":1.29122,"raw":708,"rawp":1.291,"real":43,"realp":0.47},{"name":"Breloom","usage":1.27116,"raw":697,"rawp":1.271,"real":29,"realp":0.317},{"name":"Swampert","usage":1.27116,"raw":697,"rawp":1.271,"real":424,"realp":4.639},{"name":"Thundurus","usage":1.27116,"raw":697,"rawp":1.271,"real":60,"realp":0.656},{"name":"Sceptile","usage":1.25474,"raw":688,"rawp":1.255,"real":28,"realp":0.306},{"name":"Incineroar","usage":1.23833,"raw":679,"rawp":1.238,"real":233,"realp":2.549},{"name":"Tapu Koko","usage":1.23468,"raw":677,"rawp":1.235,"real":196,"realp":2.144},{"name":"Hoopa-Unbound","usage":1.19456,"raw":655,"rawp":1.195,"real":126,"realp":1.379},{"name":"Exploud","usage":1.18544,"raw":650,"rawp":1.185,"real":68,"realp":0.744},{"name":"Hawlucha","usage":1.17632,"raw":645,"rawp":1.176,"real":85,"realp":0.93},{"name":"Barbaracle","usage":1.17267,"raw":643,"rawp":1.173,"real":29,"realp":0.317},{"name":"Squirtle","usage":1.14532,"raw":628,"rawp":1.145,"real":49,"realp":0.536},{"name":"Crawdaunt","usage":1.13437,"raw":622,"rawp":1.134,"real":108,"realp":1.182},{"name":"Drampa","usage":1.13437,"raw":622,"rawp":1.134,"real":151,"realp":1.652},{"name":"Charizard","usage":1.1289,"raw":619,"rawp":1.129,"real":51,"realp":0.558},{"name":"Regirock","usage":1.09243,"raw":599,"rawp":1.092,"real":15,"realp":0.164},{"name":"Oshawott","usage":1.08696,"raw":596,"rawp":1.087,"real":69,"realp":0.755},{"name":"Chandelure","usage":1.05413,"raw":578,"rawp":1.054,"real":78,"realp":0.853},{"name":"Quagsire","usage":1.04136,"raw":571,"rawp":1.041,"real":160,"realp":1.751},{"name":"Stufful","usage":1.04136,"raw":571,"rawp":1.041,"real":512,"realp":5.602},{"name":"Garchomp","usage":1.02495,"raw":562,"rawp":1.025,"real":37,"realp":0.405},{"name":"Deoxys","usage":1.0213,"raw":560,"rawp":1.021,"real":6,"realp":0.066},{"name":"Volcarona","usage":1.01765,"raw":558,"rawp":1.018,"real":32,"realp":0.35},{"name":"Blastoise","usage":1.01583,"raw":557,"rawp":1.016,"real":14,"realp":0.153},{"name":"Venusaur","usage":1.00124,"raw":549,"rawp":1.001,"real":106,"realp":1.16},{"name":"Latios","usage":0.98847,"raw":542,"rawp":0.988,"real":50,"realp":0.547},{"name":"Miltank","usage":0.98847,"raw":542,"rawp":0.988,"real":14,"realp":0.153},{"name":"Infernape","usage":0.93741,"raw":514,"rawp":0.937,"real":95,"realp":1.039},{"name":"Eevee","usage":0.93011,"raw":510,"rawp":0.93,"real":91,"realp":0.996},{"name":"Snorlax","usage":0.91917,"raw":504,"rawp":0.919,"real":69,"realp":0.755},{"name":"Jellicent","usage":0.90458,"raw":496,"rawp":0.905,"real":341,"realp":3.731},{"name":"Sunkern","usage":0.89729,"raw":492,"rawp":0.897,"real":50,"realp":0.547},{"name":"Sigilyph","usage":0.88634,"raw":486,"rawp":0.886,"real":9,"realp":0.098},{"name":"Spinda","usage":0.88087,"raw":483,"rawp":0.881,"real":40,"realp":0.438},{"name":"Giratina-Origin","usage":0.86446,"raw":474,"rawp":0.864,"real":104,"realp":1.138},{"name":"Cloyster","usage":0.85899,"raw":471,"rawp":0.859,"real":25,"realp":0.274},{"name":"Pichu","usage":0.83893,"raw":460,"rawp":0.839,"real":157,"realp":1.718},{"name":"Tyranitar","usage":0.82798,"raw":454,"rawp":0.828,"real":95,"realp":1.039},{"name":"Krookodile","usage":0.81522,"raw":447,"rawp":0.815,"real":46,"realp":0.503},{"name":"Empoleon","usage":0.81339,"raw":446,"rawp":0.813,"real":297,"realp":3.25},{"name":"Numel","usage":0.80245,"raw":440,"rawp":0.802,"real":69,"realp":0.755},{"name":"Tsareena","usage":0.79151,"raw":434,"rawp":0.792,"real":19,"realp":0.208},{"name":"Haxorus","usage":0.79151,"raw":434,"rawp":0.792,"real":14,"realp":0.153},{"name":"Bulbasaur","usage":0.78604,"raw":431,"rawp":0.786,"real":45,"realp":0.492},{"name":"Rotom-Heat","usage":0.78604,"raw":431,"rawp":0.786,"real":211,"realp":2.309},{"name":"Shiinotic","usage":0.76962,"raw":422,"rawp":0.77,"real":7,"realp":0.077},{"name":"Flygon","usage":0.76233,"raw":418,"rawp":0.762,"real":41,"realp":0.449},{"name":"Arceus-Ghost","usage":0.7605,"raw":417,"rawp":0.761,"real":16,"realp":0.175},{"name":"Froakie","usage":0.75686,"raw":415,"rawp":0.757,"real":3,"realp":0.033},{"name":"Bruxish","usage":0.75321,"raw":413,"rawp":0.753,"real":23,"realp":0.252},{"name":"Zapdos","usage":0.75139,"raw":412,"rawp":0.751,"real":197,"realp":2.155},{"name":"Mamoswine","usage":0.73315,"raw":402,"rawp":0.733,"real":116,"realp":1.269},{"name":"Butterfree","usage":0.73132,"raw":401,"rawp":0.731,"real":0,"realp":0},{"name":"Geodude","usage":0.73132,"raw":401,"rawp":0.731,"real":4,"realp":0.044},{"name":"Rotom-Wash","usage":0.72403,"raw":397,"rawp":0.724,"real":166,"realp":1.816},{"name":"Lopunny","usage":0.72221,"raw":396,"rawp":0.722,"real":61,"realp":0.667},{"name":"Abra","usage":0.71856,"raw":394,"rawp":0.719,"real":13,"realp":0.142},{"name":"Azumarill","usage":0.70214,"raw":385,"rawp":0.702,"real":65,"realp":0.711},{"name":"Clefairy","usage":0.70214,"raw":385,"rawp":0.702,"real":7,"realp":0.077},{"name":"Lapras","usage":0.69667,"raw":382,"rawp":0.697,"real":238,"realp":2.604},{"name":"Cresselia","usage":0.68938,"raw":378,"rawp":0.689,"real":17,"realp":0.186},{"name":"Chikorita","usage":0.68938,"raw":378,"rawp":0.689,"real":5,"realp":0.055},{"name":"Bibarel","usage":0.68755,"raw":377,"rawp":0.688,"real":71,"realp":0.777},{"name":"Machamp","usage":0.68026,"raw":373,"rawp":0.68,"real":26,"realp":0.284},{"name":"Arceus-Water","usage":0.66749,"raw":366,"rawp":0.667,"real":33,"realp":0.361},{"name":"Avalugg","usage":0.66749,"raw":366,"rawp":0.667,"real":6,"realp":0.066},{"name":"Umbreon","usage":0.66567,"raw":365,"rawp":0.666,"real":27,"realp":0.295},{"name":"Rotom-Frost","usage":0.65837,"raw":361,"rawp":0.658,"real":267,"realp":2.921},{"name":"Gardevoir","usage":0.65837,"raw":361,"rawp":0.658,"real":100,"realp":1.094},{"name":"Salandit","usage":0.6529,"raw":358,"rawp":0.653,"real":64,"realp":0.7},{"name":"Linoone","usage":0.64926,"raw":356,"rawp":0.649,"real":11,"realp":0.12},{"name":"Dewpider","usage":0.64926,"raw":356,"rawp":0.649,"real":66,"realp":0.722},{"name":"Drapion","usage":0.63831,"raw":350,"rawp":0.638,"real":282,"realp":3.085},{"name":"Trevenant","usage":0.63467,"raw":348,"rawp":0.635,"real":128,"realp":1.4},{"name":"Pelipper","usage":0.63467,"raw":348,"rawp":0.635,"real":21,"realp":0.23},{"name":"Mr. Mime","usage":0.63102,"raw":346,"rawp":0.631,"real":70,"realp":0.766},{"name":"Diancie","usage":0.62737,"raw":344,"rawp":0.627,"real":61,"realp":0.667},{"name":"Tapu Bulu","usage":0.62372,"raw":342,"rawp":0.624,"real":23,"realp":0.252},{"name":"Gallade","usage":0.62372,"raw":342,"rawp":0.624,"real":36,"realp":0.394},{"name":"Greninja-Ash","usage":0.62372,"raw":342,"rawp":0.624,"real":23,"realp":0.252},{"name":"Steelix","usage":0.6146,"raw":337,"rawp":0.615,"real":69,"realp":0.755},{"name":"Shaymin-Sky","usage":0.60913,"raw":334,"rawp":0.609,"real":36,"realp":0.394},{"name":"Bisharp","usage":0.60731,"raw":333,"rawp":0.607,"real":109,"realp":1.193},{"name":"Ambipom","usage":0.60184,"raw":330,"rawp":0.602,"real":25,"realp":0.274},{"name":"Xurkitree","usage":0.5909,"raw":324,"rawp":0.591,"real":74,"realp":0.81},{"name":"Natu","usage":0.5909,"raw":324,"rawp":0.591,"real":2,"realp":0.022},{"name":"Kadabra","usage":0.58907,"raw":323,"rawp":0.589,"real":1,"realp":0.011},{"name":"Weavile","usage":0.58725,"raw":322,"rawp":0.587,"real":55,"realp":0.602},{"name":"Meowstic","usage":0.58725,"raw":322,"rawp":0.587,"real":13,"realp":0.142},{"name":"Crabominable","usage":0.58542,"raw":321,"rawp":0.585,"real":60,"realp":0.656},{"name":"Feebas","usage":0.58542,"raw":321,"rawp":0.585,"real":5,"realp":0.055},{"name":"Reuniclus","usage":0.58178,"raw":319,"rawp":0.582,"real":35,"realp":0.383},{"name":"Guzzlord","usage":0.57995,"raw":318,"rawp":0.58,"real":25,"realp":0.274},{"name":"Exeggutor-Alola","usage":0.57995,"raw":318,"rawp":0.58,"real":16,"realp":0.175},{"name":"Starmie","usage":0.57631,"raw":316,"rawp":0.576,"real":25,"realp":0.274},{"name":"Scrafty","usage":0.57083,"raw":313,"rawp":0.571,"real":35,"realp":0.383},{"name":"Bewear","usage":0.56172,"raw":308,"rawp":0.562,"real":162,"realp":1.772},{"name":"Raichu-Alola","usage":0.5526,"raw":303,"rawp":0.553,"real":71,"realp":0.777},{"name":"Kangaskhan","usage":0.54895,"raw":301,"rawp":0.549,"real":30,"realp":0.328},{"name":"Rhyperior","usage":0.54713,"raw":300,"rawp":0.547,"real":18,"realp":0.197},{"name":"Manaphy","usage":0.5453,"raw":299,"rawp":0.545,"real":8,"realp":0.088},{"name":"Toucannon","usage":0.5453,"raw":299,"rawp":0.545,"real":13,"realp":0.142},{"name":"Azurill","usage":0.54348,"raw":298,"rawp":0.543,"real":121,"realp":1.324},{"name":"Camerupt","usage":0.54348,"raw":298,"rawp":0.543,"real":133,"realp":1.455},{"name":"Charmander","usage":0.54165,"raw":297,"rawp":0.542,"real":27,"realp":0.295},{"name":"Rattata","usage":0.54165,"raw":297,"rawp":0.542,"real":76,"realp":0.832},{"name":"Slakoth","usage":0.53618,"raw":294,"rawp":0.536,"real":8,"realp":0.088},{"name":"Volbeat","usage":0.53618,"raw":294,"rawp":0.536,"real":6,"realp":0.066},{"name":"Basculin","usage":0.53254,"raw":292,"rawp":0.533,"real":63,"realp":0.689},{"name":"Necrozma","usage":0.53254,"raw":292,"rawp":0.533,"real":11,"realp":0.12},{"name":"Carbink","usage":0.52889,"raw":290,"rawp":0.529,"real":4,"realp":0.044},{"name":"Arceus-Steel","usage":0.52524,"raw":288,"rawp":0.525,"real":55,"realp":0.602},{"name":"Keldeo","usage":0.52524,"raw":288,"rawp":0.525,"real":36,"realp":0.394},{"name":"Forretress","usage":0.52524,"raw":288,"rawp":0.525,"real":196,"realp":2.144},{"name":"Heracross","usage":0.52342,"raw":287,"rawp":0.523,"real":24,"realp":0.263},{"name":"Latias","usage":0.52159,"raw":286,"rawp":0.522,"real":20,"realp":0.219},{"name":"Geodude-Alola","usage":0.51977,"raw":285,"rawp":0.52,"real":3,"realp":0.033},{"name":"Raichu","usage":0.51247,"raw":281,"rawp":0.512,"real":18,"realp":0.197},{"name":"Dhelmise","usage":0.51065,"raw":280,"rawp":0.511,"real":22,"realp":0.241},{"name":"Sawk","usage":0.50883,"raw":279,"rawp":0.509,"real":25,"realp":0.274},{"name":"Aron","usage":0.507,"raw":278,"rawp":0.507,"real":46,"realp":0.503},{"name":"Chimecho","usage":0.507,"raw":278,"rawp":0.507,"real":1,"realp":0.011},{"name":"Dragalge","usage":0.50518,"raw":277,"rawp":0.505,"real":33,"realp":0.361},{"name":"Gyarados","usage":0.50336,"raw":276,"rawp":0.503,"real":51,"realp":0.558},{"name":"Accelgor","usage":0.49788,"raw":273,"rawp":0.498,"real":1,"realp":0.011},{"name":"Slowbro","usage":0.49059,"raw":269,"rawp":0.491,"real":14,"realp":0.153},{"name":"Rampardos","usage":0.49059,"raw":269,"rawp":0.491,"real":6,"realp":0.066},{"name":"Tapu Fini","usage":0.48512,"raw":266,"rawp":0.485,"real":44,"realp":0.481},{"name":"Ludicolo","usage":0.48512,"raw":266,"rawp":0.485,"real":49,"realp":0.536},{"name":"Cottonee","usage":0.47782,"raw":262,"rawp":0.478,"real":15,"realp":0.164},{"name":"Wailord","usage":0.476,"raw":261,"rawp":0.476,"real":52,"realp":0.569},{"name":"Cosmog","usage":0.476,"raw":261,"rawp":0.476,"real":70,"realp":0.766},{"name":"Arceus-Fighting","usage":0.47235,"raw":259,"rawp":0.472,"real":5,"realp":0.055},{"name":"Carracosta","usage":0.47053,"raw":258,"rawp":0.471,"real":11,"realp":0.12},{"name":"Honchkrow","usage":0.46323,"raw":254,"rawp":0.463,"real":30,"realp":0.328},{"name":"Ninjask","usage":0.46323,"raw":254,"rawp":0.463,"real":9,"realp":0.098},{"name":"Chesnaught","usage":0.46141,"raw":253,"rawp":0.461,"real":6,"realp":0.066},{"name":"Regice","usage":0.46141,"raw":253,"rawp":0.461,"real":9,"realp":0.098},{"name":"Arceus-Fairy","usage":0.45229,"raw":248,"rawp":0.452,"real":10,"realp":0.109},{"name":"Gastrodon","usage":0.45047,"raw":247,"rawp":0.45,"real":91,"realp":0.996},{"name":"Sudowoodo","usage":0.44864,"raw":246,"rawp":0.449,"real":4,"realp":0.044},{"name":"Rotom","usage":0.44135,"raw":242,"rawp":0.441,"real":159,"realp":1.74},{"name":"Noivern","usage":0.4377,"raw":240,"rawp":0.438,"real":25,"realp":0.274},{"name":"Lanturn","usage":0.4377,"raw":240,"rawp":0.438,"real":75,"realp":0.821},{"name":"Houndoom","usage":0.43405,"raw":238,"rawp":0.434,"real":26,"realp":0.284},{"name":"Stunky","usage":0.43223,"raw":237,"rawp":0.432,"real":232,"realp":2.538},{"name":"Darkrai","usage":0.43041,"raw":236,"rawp":0.43,"real":48,"realp":0.525},{"name":"Staryu","usage":0.43041,"raw":236,"rawp":0.43,"real":0,"realp":0},{"name":"Tropius","usage":0.43041,"raw":236,"rawp":0.43,"real":42,"realp":0.46},{"name":"Kommo-o","usage":0.42676,"raw":234,"rawp":0.427,"real":24,"realp":0.263},{"name":"Magnemite","usage":0.42129,"raw":231,"rawp":0.421,"real":53,"realp":0.58},{"name":"Hariyama","usage":0.41946,"raw":230,"rawp":0.419,"real":24,"realp":0.263},{"name":"Diglett","usage":0.41764,"raw":229,"rawp":0.418,"real":81,"realp":0.886},{"name":"Cinccino","usage":0.41764,"raw":229,"rawp":0.418,"real":10,"realp":0.109},{"name":"Litwick","usage":0.41764,"raw":229,"rawp":0.418,"real":91,"realp":0.996},{"name":"Roserade","usage":0.41582,"raw":228,"rawp":0.416,"real":154,"realp":1.685},{"name":"Amaura","usage":0.41399,"raw":227,"rawp":0.414,"real":8,"realp":0.088},{"name":"Staraptor","usage":0.41217,"raw":226,"rawp":0.412,"real":21,"realp":0.23},{"name":"Meloetta","usage":0.4067,"raw":223,"rawp":0.407,"real":126,"realp":1.379},{"name":"Buzzwole","usage":0.40123,"raw":220,"rawp":0.401,"real":45,"realp":0.492},{"name":"Cradily","usage":0.40123,"raw":220,"rawp":0.401,"real":81,"realp":0.886},{"name":"Diggersby","usage":0.3994,"raw":219,"rawp":0.399,"real":102,"realp":1.116},{"name":"Arceus-Dark","usage":0.39575,"raw":217,"rawp":0.396,"real":5,"realp":0.055},{"name":"Chingling","usage":0.39211,"raw":215,"rawp":0.392,"real":3,"realp":0.033},{"name":"Woobat","usage":0.39028,"raw":214,"rawp":0.39,"real":11,"realp":0.12},{"name":"Dunsparce","usage":0.39028,"raw":214,"rawp":0.39,"real":55,"realp":0.602},{"name":"Tornadus","usage":0.38846,"raw":213,"rawp":0.388,"real":27,"realp":0.295},{"name":"Drifblim","usage":0.38481,"raw":211,"rawp":0.385,"real":146,"realp":1.597},{"name":"Zubat","usage":0.38481,"raw":211,"rawp":0.385,"real":66,"realp":0.722},{"name":"Registeel","usage":0.38299,"raw":210,"rawp":0.383,"real":30,"realp":0.328},{"name":"Arceus-Ground","usage":0.38116,"raw":209,"rawp":0.381,"real":13,"realp":0.142},{"name":"Cosmoem","usage":0.38116,"raw":209,"rawp":0.381,"real":19,"realp":0.208},{"name":"Groudon-Primal","usage":0.38116,"raw":209,"rawp":0.381,"real":39,"realp":0.427},{"name":"Wishiwashi","usage":0.37934,"raw":208,"rawp":0.379,"real":46,"realp":0.503},{"name":"Mime Jr.","usage":0.37752,"raw":207,"rawp":0.378,"real":33,"realp":0.361},{"name":"Thundurus-Therian","usage":0.37752,"raw":207,"rawp":0.378,"real":96,"realp":1.05},{"name":"Crobat","usage":0.37205,"raw":204,"rawp":0.372,"real":71,"realp":0.777},{"name":"Ninetales","usage":0.37022,"raw":203,"rawp":0.37,"real":5,"realp":0.055},{"name":"Unown","usage":0.37022,"raw":203,"rawp":0.37,"real":49,"realp":0.536},{"name":"Bastiodon","usage":0.3684,"raw":202,"rawp":0.368,"real":5,"realp":0.055},{"name":"Haunter","usage":0.35928,"raw":197,"rawp":0.359,"real":69,"realp":0.755},{"name":"Binacle","usage":0.35928,"raw":197,"rawp":0.359,"real":0,"realp":0},{"name":"Metagross","usage":0.35928,"raw":197,"rawp":0.359,"real":63,"realp":0.689},{"name":"Cacturne","usage":0.35746,"raw":196,"rawp":0.357,"real":21,"realp":0.23},{"name":"Lurantis","usage":0.35381,"raw":194,"rawp":0.354,"real":2,"realp":0.022},{"name":"Pidgey","usage":0.35381,"raw":194,"rawp":0.354,"real":81,"realp":0.886},{"name":"Gourgeist-Super","usage":0.35381,"raw":194,"rawp":0.354,"real":9,"realp":0.098},{"name":"Dusknoir","usage":0.34651,"raw":190,"rawp":0.347,"real":66,"realp":0.722},{"name":"Cryogonal","usage":0.34651,"raw":190,"rawp":0.347,"real":12,"realp":0.131},{"name":"Sandslash-Alola","usage":0.34104,"raw":187,"rawp":0.341,"real":16,"realp":0.175},{"name":"Typhlosion","usage":0.34104,"raw":187,"rawp":0.341,"real":13,"realp":0.142},{"name":"Entei","usage":0.33739,"raw":185,"rawp":0.337,"real":7,"realp":0.077},{"name":"Venonat","usage":0.33557,"raw":184,"rawp":0.336,"real":2,"realp":0.022},{"name":"Rattata-Alola","usage":0.33557,"raw":184,"rawp":0.336,"real":135,"realp":1.477},{"name":"Kyogre-Primal","usage":0.33557,"raw":184,"rawp":0.336,"real":20,"realp":0.219},{"name":"Golurk","usage":0.33375,"raw":183,"rawp":0.334,"real":63,"realp":0.689},{"name":"Suicune","usage":0.33375,"raw":183,"rawp":0.334,"real":77,"realp":0.842},{"name":"Barboach","usage":0.33192,"raw":182,"rawp":0.332,"real":164,"realp":1.794},{"name":"Venomoth","usage":0.33192,"raw":182,"rawp":0.332,"real":2,"realp":0.022},{"name":"Sandygast","usage":0.3301,"raw":181,"rawp":0.33,"real":100,"realp":1.094},{"name":"Oricorio-Pom-Pom","usage":0.32645,"raw":179,"rawp":0.326,"real":23,"realp":0.252},{"name":"Decidueye","usage":0.32645,"raw":179,"rawp":0.326,"real":30,"realp":0.328},{"name":"Arceus-Dragon","usage":0.32463,"raw":178,"rawp":0.325,"real":5,"realp":0.055},{"name":"Cleffa","usage":0.32463,"raw":178,"rawp":0.325,"real":20,"realp":0.219},{"name":"Bonsly","usage":0.32463,"raw":178,"rawp":0.325,"real":4,"realp":0.044},{"name":"Misdreavus","usage":0.3228,"raw":177,"rawp":0.323,"real":96,"realp":1.05},{"name":"Turtonator","usage":0.3228,"raw":177,"rawp":0.323,"real":40,"realp":0.438},{"name":"Ninetales-Alola","usage":0.31916,"raw":175,"rawp":0.319,"real":44,"realp":0.481},{"name":"Lycanroc-Dusk","usage":0.31733,"raw":174,"rawp":0.317,"real":2,"realp":0.022},{"name":"Vulpix","usage":0.31733,"raw":174,"rawp":0.317,"real":2,"realp":0.022},{"name":"Corsola","usage":0.31733,"raw":174,"rawp":0.317,"real":4,"realp":0.044},{"name":"Porygon2","usage":0.31733,"raw":174,"rawp":0.317,"real":59,"realp":0.646},{"name":"Klinklang","usage":0.31733,"raw":174,"rawp":0.317,"real":11,"realp":0.12},{"name":"Helioptile","usage":0.31733,"raw":174,"rawp":0.317,"real":3,"realp":0.033},{"name":"Minior","usage":0.31733,"raw":174,"rawp":0.317,"real":10,"realp":0.109},{"name":"Zygarde-10%","usage":0.31551,"raw":173,"rawp":0.316,"real":5,"realp":0.055},{"name":"Pineco","usage":0.31186,"raw":171,"rawp":0.312,"real":1,"realp":0.011},{"name":"Wigglytuff","usage":0.30821,"raw":169,"rawp":0.308,"real":54,"realp":0.591},{"name":"Hydreigon","usage":0.30639,"raw":168,"rawp":0.306,"real":23,"realp":0.252},{"name":"Dewgong","usage":0.30639,"raw":168,"rawp":0.306,"real":29,"realp":0.317},{"name":"Liepard","usage":0.30092,"raw":165,"rawp":0.301,"real":7,"realp":0.077},{"name":"Darmanitan","usage":0.29727,"raw":163,"rawp":0.297,"real":44,"realp":0.481},{"name":"Jynx","usage":0.29727,"raw":163,"rawp":0.297,"real":9,"realp":0.098},{"name":"Donphan","usage":0.29727,"raw":163,"rawp":0.297,"real":2,"realp":0.022},{"name":"Vivillon","usage":0.29545,"raw":162,"rawp":0.295,"real":4,"realp":0.044},{"name":"Pawniard","usage":0.2918,"raw":160,"rawp":0.292,"real":132,"realp":1.444},{"name":"Medicham","usage":0.2918,"raw":160,"rawp":0.292,"real":16,"realp":0.175},{"name":"Yanmega","usage":0.2918,"raw":160,"rawp":0.292,"real":1,"realp":0.011},{"name":"Arceus-Electric","usage":0.28998,"raw":159,"rawp":0.29,"real":21,"realp":0.23},{"name":"Inkay","usage":0.28998,"raw":159,"rawp":0.29,"real":29,"realp":0.317},{"name":"Raticate-Alola","usage":0.28998,"raw":159,"rawp":0.29,"real":87,"realp":0.952},{"name":"Scolipede","usage":0.28633,"raw":157,"rawp":0.286,"real":12,"realp":0.131},{"name":"Landorus","usage":0.28451,"raw":156,"rawp":0.285,"real":43,"realp":0.47},{"name":"Bouffalant","usage":0.27903,"raw":153,"rawp":0.279,"real":33,"realp":0.361},{"name":"Jolteon","usage":0.27903,"raw":153,"rawp":0.279,"real":40,"realp":0.438},{"name":"Arceus-Flying","usage":0.27903,"raw":153,"rawp":0.279,"real":11,"realp":0.12},{"name":"Poliwrath","usage":0.27721,"raw":152,"rawp":0.277,"real":20,"realp":0.219},{"name":"Skuntank","usage":0.27539,"raw":151,"rawp":0.275,"real":124,"realp":1.357},{"name":"Taillow","usage":0.27539,"raw":151,"rawp":0.275,"real":11,"realp":0.12},{"name":"Grimer-Alola","usage":0.27539,"raw":151,"rawp":0.275,"real":124,"realp":1.357},{"name":"Milotic","usage":0.27539,"raw":151,"rawp":0.275,"real":20,"realp":0.219},{"name":"Sharpedo","usage":0.27174,"raw":149,"rawp":0.272,"real":14,"realp":0.153},{"name":"Tangrowth","usage":0.26992,"raw":148,"rawp":0.27,"real":11,"realp":0.12},{"name":"Conkeldurr","usage":0.26992,"raw":148,"rawp":0.27,"real":15,"realp":0.164},{"name":"Ralts","usage":0.26809,"raw":147,"rawp":0.268,"real":53,"realp":0.58},{"name":"Magcargo","usage":0.26627,"raw":146,"rawp":0.266,"real":23,"realp":0.252},{"name":"Gigalith","usage":0.26627,"raw":146,"rawp":0.266,"real":2,"realp":0.022},{"name":"Altaria","usage":0.2608,"raw":143,"rawp":0.261,"real":4,"realp":0.044},{"name":"Palossand","usage":0.2608,"raw":143,"rawp":0.261,"real":34,"realp":0.372},{"name":"Zigzagoon","usage":0.2608,"raw":143,"rawp":0.261,"real":21,"realp":0.23},{"name":"Raticate","usage":0.25897,"raw":142,"rawp":0.259,"real":4,"realp":0.044},{"name":"Marowak","usage":0.25897,"raw":142,"rawp":0.259,"real":23,"realp":0.252},{"name":"Golisopod","usage":0.25715,"raw":141,"rawp":0.257,"real":36,"realp":0.394},{"name":"Abomasnow","usage":0.25715,"raw":141,"rawp":0.257,"real":44,"realp":0.481},{"name":"Arceus-Fire","usage":0.25715,"raw":141,"rawp":0.257,"real":17,"realp":0.186},{"name":"Armaldo","usage":0.25533,"raw":140,"rawp":0.255,"real":14,"realp":0.153},{"name":"Phantump","usage":0.2535,"raw":139,"rawp":0.254,"real":45,"realp":0.492},{"name":"Dusclops","usage":0.2535,"raw":139,"rawp":0.254,"real":59,"realp":0.646},{"name":"Hoopa","usage":0.25168,"raw":138,"rawp":0.252,"real":58,"realp":0.635},{"name":"Dratini","usage":0.24985,"raw":137,"rawp":0.25,"real":7,"realp":0.077},{"name":"Vespiquen","usage":0.24803,"raw":136,"rawp":0.248,"real":0,"realp":0},{"name":"Psyduck","usage":0.24621,"raw":135,"rawp":0.246,"real":18,"realp":0.197},{"name":"Feraligatr","usage":0.24438,"raw":134,"rawp":0.244,"real":61,"realp":0.667},{"name":"Graveler-Alola","usage":0.24438,"raw":134,"rawp":0.244,"real":2,"realp":0.022},{"name":"Clawitzer","usage":0.24256,"raw":133,"rawp":0.243,"real":26,"realp":0.284},{"name":"Torkoal","usage":0.24074,"raw":132,"rawp":0.241,"real":2,"realp":0.022},{"name":"Clamperl","usage":0.23891,"raw":131,"rawp":0.239,"real":120,"realp":1.313},{"name":"Nidoqueen","usage":0.23891,"raw":131,"rawp":0.239,"real":8,"realp":0.088},{"name":"Duskull","usage":0.23891,"raw":131,"rawp":0.239,"real":75,"realp":0.821},{"name":"Heatmor","usage":0.23891,"raw":131,"rawp":0.239,"real":4,"realp":0.044},{"name":"Lilligant","usage":0.23891,"raw":131,"rawp":0.239,"real":3,"realp":0.033},{"name":"Wormadam-Trash","usage":0.23709,"raw":130,"rawp":0.237,"real":89,"realp":0.974},{"name":"Kingdra","usage":0.23709,"raw":130,"rawp":0.237,"real":93,"realp":1.018},{"name":"Octillery","usage":0.23526,"raw":129,"rawp":0.235,"real":11,"realp":0.12},{"name":"Crustle","usage":0.23526,"raw":129,"rawp":0.235,"real":11,"realp":0.12},{"name":"Cofagrigus","usage":0.23526,"raw":129,"rawp":0.235,"real":15,"realp":0.164},{"name":"Girafarig","usage":0.23344,"raw":128,"rawp":0.233,"real":23,"realp":0.252},{"name":"Caterpie","usage":0.23162,"raw":127,"rawp":0.232,"real":25,"realp":0.274},{"name":"Tangela","usage":0.22979,"raw":126,"rawp":0.23,"real":34,"realp":0.372},{"name":"Primarina","usage":0.22979,"raw":126,"rawp":0.23,"real":46,"realp":0.503},{"name":"Gourgeist","usage":0.22979,"raw":126,"rawp":0.23,"real":0,"realp":0},{"name":"Gogoat","usage":0.22797,"raw":125,"rawp":0.228,"real":9,"realp":0.098},{"name":"Yungoos","usage":0.22797,"raw":125,"rawp":0.228,"real":1,"realp":0.011},{"name":"Weedle","usage":0.22615,"raw":124,"rawp":0.226,"real":35,"realp":0.383},{"name":"Shiftry","usage":0.22432,"raw":123,"rawp":0.224,"real":16,"realp":0.175},{"name":"Ferroseed","usage":0.2225,"raw":122,"rawp":0.222,"real":77,"realp":0.842},{"name":"Archeops","usage":0.2225,"raw":122,"rawp":0.222,"real":72,"realp":0.788},{"name":"Drifloon","usage":0.2225,"raw":122,"rawp":0.222,"real":113,"realp":1.236},{"name":"Mismagius","usage":0.22067,"raw":121,"rawp":0.221,"real":33,"realp":0.361},{"name":"Salamence","usage":0.22067,"raw":121,"rawp":0.221,"real":16,"realp":0.175},{"name":"Pansage","usage":0.21885,"raw":120,"rawp":0.219,"real":1,"realp":0.011},{"name":"Goodra","usage":0.21885,"raw":120,"rawp":0.219,"real":7,"realp":0.077},{"name":"Eelektross","usage":0.21885,"raw":120,"rawp":0.219,"real":47,"realp":0.514},{"name":"Mudkip","usage":0.21885,"raw":120,"rawp":0.219,"real":19,"realp":0.208},{"name":"Hitmonlee","usage":0.21885,"raw":120,"rawp":0.219,"real":1,"realp":0.011},{"name":"Tynamo","usage":0.21885,"raw":120,"rawp":0.219,"real":70,"realp":0.766},{"name":"Swellow","usage":0.21703,"raw":119,"rawp":0.217,"real":7,"realp":0.077},{"name":"Zoroark","usage":0.21703,"raw":119,"rawp":0.217,"real":6,"realp":0.066},{"name":"Slugma","usage":0.21703,"raw":119,"rawp":0.217,"real":7,"realp":0.077},{"name":"Oddish","usage":0.21703,"raw":119,"rawp":0.217,"real":37,"realp":0.405},{"name":"Druddigon","usage":0.2152,"raw":118,"rawp":0.215,"real":9,"realp":0.098},{"name":"Marill","usage":0.2152,"raw":118,"rawp":0.215,"real":58,"realp":0.635},{"name":"Naganadel","usage":0.21338,"raw":117,"rawp":0.213,"real":36,"realp":0.394},{"name":"Golem","usage":0.21338,"raw":117,"rawp":0.213,"real":4,"realp":0.044},{"name":"Primeape","usage":0.21338,"raw":117,"rawp":0.213,"real":0,"realp":0},{"name":"Dedenne","usage":0.21156,"raw":116,"rawp":0.212,"real":41,"realp":0.449},{"name":"Oricorio-Sensu","usage":0.21156,"raw":116,"rawp":0.212,"real":15,"realp":0.164},{"name":"Banette","usage":0.21156,"raw":116,"rawp":0.212,"real":25,"realp":0.274},{"name":"Wobbuffet","usage":0.20608,"raw":113,"rawp":0.206,"real":30,"realp":0.328},{"name":"Jumpluff","usage":0.20608,"raw":113,"rawp":0.206,"real":28,"realp":0.306},{"name":"Maractus","usage":0.20608,"raw":113,"rawp":0.206,"real":3,"realp":0.033},{"name":"Bronzong","usage":0.20608,"raw":113,"rawp":0.206,"real":9,"realp":0.098},{"name":"Jigglypuff","usage":0.20244,"raw":111,"rawp":0.202,"real":56,"realp":0.613},{"name":"Hypno","usage":0.20244,"raw":111,"rawp":0.202,"real":0,"realp":0},{"name":"Aipom","usage":0.20061,"raw":110,"rawp":0.201,"real":18,"realp":0.197},{"name":"Arceus-Poison","usage":0.20061,"raw":110,"rawp":0.201,"real":6,"realp":0.066},{"name":"Tornadus-Therian","usage":0.19879,"raw":109,"rawp":0.199,"real":67,"realp":0.733},{"name":"Spritzee","usage":0.19697,"raw":108,"rawp":0.197,"real":0,"realp":0},{"name":"Probopass","usage":0.19697,"raw":108,"rawp":0.197,"real":6,"realp":0.066},{"name":"Oricorio","usage":0.19514,"raw":107,"rawp":0.195,"real":20,"realp":0.219},{"name":"Toxicroak","usage":0.19332,"raw":106,"rawp":0.193,"real":23,"realp":0.252},{"name":"Gumshoos","usage":0.19332,"raw":106,"rawp":0.193,"real":16,"realp":0.175},{"name":"Bergmite","usage":0.19149,"raw":105,"rawp":0.191,"real":11,"realp":0.12},{"name":"Sawsbuck","usage":0.19149,"raw":105,"rawp":0.191,"real":24,"realp":0.263},{"name":"Flareon","usage":0.19149,"raw":105,"rawp":0.191,"real":2,"realp":0.022},{"name":"Klink","usage":0.18785,"raw":103,"rawp":0.188,"real":47,"realp":0.514},{"name":"Seismitoad","usage":0.18785,"raw":103,"rawp":0.188,"real":51,"realp":0.558},{"name":"Electivire","usage":0.18785,"raw":103,"rawp":0.188,"real":28,"realp":0.306},{"name":"Arceus-Psychic","usage":0.18602,"raw":102,"rawp":0.186,"real":4,"realp":0.044},{"name":"Stoutland","usage":0.18602,"raw":102,"rawp":0.186,"real":33,"realp":0.361},{"name":"Purrloin","usage":0.18602,"raw":102,"rawp":0.186,"real":0,"realp":0},{"name":"Shuppet","usage":0.18238,"raw":100,"rawp":0.182,"real":79,"realp":0.864},{"name":"Togetic","usage":0.18055,"raw":99,"rawp":0.181,"real":34,"realp":0.372},{"name":"Pinsir","usage":0.18055,"raw":99,"rawp":0.181,"real":0,"realp":0},{"name":"Chatot","usage":0.18055,"raw":99,"rawp":0.181,"real":4,"realp":0.044},{"name":"Fletchling","usage":0.18055,"raw":99,"rawp":0.181,"real":0,"realp":0},{"name":"Magneton","usage":0.17873,"raw":98,"rawp":0.179,"real":28,"realp":0.306},{"name":"Exeggcute","usage":0.17873,"raw":98,"rawp":0.179,"real":32,"realp":0.35},{"name":"Hitmontop","usage":0.17873,"raw":98,"rawp":0.179,"real":6,"realp":0.066},{"name":"Fletchinder","usage":0.1769,"raw":97,"rawp":0.177,"real":75,"realp":0.821},{"name":"Bellossom","usage":0.1769,"raw":97,"rawp":0.177,"real":8,"realp":0.088},{"name":"Simisage","usage":0.1769,"raw":97,"rawp":0.177,"real":1,"realp":0.011},{"name":"Raikou","usage":0.1769,"raw":97,"rawp":0.177,"real":21,"realp":0.23},{"name":"Aerodactyl","usage":0.17508,"raw":96,"rawp":0.175,"real":30,"realp":0.328},{"name":"Tyrunt","usage":0.17508,"raw":96,"rawp":0.175,"real":9,"realp":0.098},{"name":"Igglybuff","usage":0.17326,"raw":95,"rawp":0.173,"real":43,"realp":0.47},{"name":"Torterra","usage":0.16961,"raw":93,"rawp":0.17,"real":15,"realp":0.164},{"name":"Diglett-Alola","usage":0.16779,"raw":92,"rawp":0.168,"real":30,"realp":0.328},{"name":"Escavalier","usage":0.16779,"raw":92,"rawp":0.168,"real":43,"realp":0.47},{"name":"Munchlax","usage":0.16779,"raw":92,"rawp":0.168,"real":27,"realp":0.295},{"name":"Slowpoke","usage":0.16596,"raw":91,"rawp":0.166,"real":5,"realp":0.055},{"name":"Piplup","usage":0.16596,"raw":91,"rawp":0.166,"real":12,"realp":0.131},{"name":"Absol","usage":0.16414,"raw":90,"rawp":0.164,"real":6,"realp":0.066},{"name":"Porygon","usage":0.16414,"raw":90,"rawp":0.164,"real":0,"realp":0},{"name":"Moltres","usage":0.16414,"raw":90,"rawp":0.164,"real":32,"realp":0.35},{"name":"Victreebel","usage":0.16414,"raw":90,"rawp":0.164,"real":5,"realp":0.055},{"name":"Arceus-Bug","usage":0.16231,"raw":89,"rawp":0.162,"real":2,"realp":0.022},{"name":"Nosepass","usage":0.16231,"raw":89,"rawp":0.162,"real":0,"realp":0},{"name":"Pyroar","usage":0.16231,"raw":89,"rawp":0.162,"real":69,"realp":0.755},{"name":"Politoed","usage":0.16049,"raw":88,"rawp":0.16,"real":3,"realp":0.033},{"name":"Sandshrew-Alola","usage":0.15867,"raw":87,"rawp":0.159,"real":52,"realp":0.569},{"name":"Swinub","usage":0.15867,"raw":87,"rawp":0.159,"real":38,"realp":0.416},{"name":"Arbok","usage":0.15867,"raw":87,"rawp":0.159,"real":2,"realp":0.022},{"name":"Solosis","usage":0.15867,"raw":87,"rawp":0.159,"real":30,"realp":0.328},{"name":"Machop","usage":0.15867,"raw":87,"rawp":0.159,"real":4,"realp":0.044},{"name":"Remoraid","usage":0.15684,"raw":86,"rawp":0.157,"real":0,"realp":0},{"name":"Mudsdale","usage":0.15684,"raw":86,"rawp":0.157,"real":2,"realp":0.022},{"name":"Dodrio","usage":0.15502,"raw":85,"rawp":0.155,"real":14,"realp":0.153},{"name":"Vileplume","usage":0.15502,"raw":85,"rawp":0.155,"real":1,"realp":0.011},{"name":"Seel","usage":0.1532,"raw":84,"rawp":0.153,"real":0,"realp":0},{"name":"Masquerain","usage":0.14955,"raw":82,"rawp":0.15,"real":2,"realp":0.022},{"name":"Shroomish","usage":0.14772,"raw":81,"rawp":0.148,"real":0,"realp":0},{"name":"Emboar","usage":0.14772,"raw":81,"rawp":0.148,"real":18,"realp":0.197},{"name":"Pachirisu","usage":0.1459,"raw":80,"rawp":0.146,"real":30,"realp":0.328},{"name":"Totodile","usage":0.1459,"raw":80,"rawp":0.146,"real":14,"realp":0.153},{"name":"Ribombee","usage":0.1459,"raw":80,"rawp":0.146,"real":9,"realp":0.098},{"name":"Axew","usage":0.14408,"raw":79,"rawp":0.144,"real":21,"realp":0.23},{"name":"Slowking","usage":0.14408,"raw":79,"rawp":0.144,"real":12,"realp":0.131},{"name":"Spoink","usage":0.14408,"raw":79,"rawp":0.144,"real":1,"realp":0.011},{"name":"Castform","usage":0.14225,"raw":78,"rawp":0.142,"real":21,"realp":0.23},{"name":"Arceus-Ice","usage":0.14043,"raw":77,"rawp":0.14,"real":3,"realp":0.033},{"name":"Togepi","usage":0.13861,"raw":76,"rawp":0.139,"real":18,"realp":0.197},{"name":"Hitmonchan","usage":0.13861,"raw":76,"rawp":0.139,"real":2,"realp":0.022},{"name":"Cyndaquil","usage":0.13861,"raw":76,"rawp":0.139,"real":14,"realp":0.153},{"name":"Beedrill","usage":0.13861,"raw":76,"rawp":0.139,"real":5,"realp":0.055},{"name":"Audino","usage":0.13861,"raw":76,"rawp":0.139,"real":5,"realp":0.055},{"name":"Pancham","usage":0.13861,"raw":76,"rawp":0.139,"real":4,"realp":0.044},{"name":"Lotad","usage":0.13861,"raw":76,"rawp":0.139,"real":40,"realp":0.438},{"name":"Claydol","usage":0.13678,"raw":75,"rawp":0.137,"real":15,"realp":0.164},{"name":"Gligar","usage":0.13496,"raw":74,"rawp":0.135,"real":26,"realp":0.284},{"name":"Deerling","usage":0.13496,"raw":74,"rawp":0.135,"real":4,"realp":0.044},{"name":"Mienshao","usage":0.13496,"raw":74,"rawp":0.135,"real":1,"realp":0.011},{"name":"Exeggutor","usage":0.13313,"raw":73,"rawp":0.133,"real":14,"realp":0.153},{"name":"Arceus-Rock","usage":0.13313,"raw":73,"rawp":0.133,"real":9,"realp":0.098},{"name":"Frillish","usage":0.13313,"raw":73,"rawp":0.133,"real":40,"realp":0.438},{"name":"Farfetch'd","usage":0.13313,"raw":73,"rawp":0.133,"real":18,"realp":0.197},{"name":"Ekans","usage":0.13313,"raw":73,"rawp":0.133,"real":3,"realp":0.033},{"name":"Happiny","usage":0.13313,"raw":73,"rawp":0.133,"real":25,"realp":0.274},{"name":"Darumaka","usage":0.13313,"raw":73,"rawp":0.133,"real":9,"realp":0.098},{"name":"Zebstrika","usage":0.13131,"raw":72,"rawp":0.131,"real":12,"realp":0.131},{"name":"Minun","usage":0.13131,"raw":72,"rawp":0.131,"real":12,"realp":0.131},{"name":"Elgyem","usage":0.13131,"raw":72,"rawp":0.131,"real":0,"realp":0},{"name":"Electrode","usage":0.12949,"raw":71,"rawp":0.129,"real":16,"realp":0.175},{"name":"Lycanroc","usage":0.12949,"raw":71,"rawp":0.129,"real":0,"realp":0},{"name":"Tentacruel","usage":0.12766,"raw":70,"rawp":0.128,"real":16,"realp":0.175},{"name":"Petilil","usage":0.12766,"raw":70,"rawp":0.128,"real":2,"realp":0.022},{"name":"Houndour","usage":0.12584,"raw":69,"rawp":0.126,"real":15,"realp":0.164},{"name":"Shaymin","usage":0.12402,"raw":68,"rawp":0.124,"real":1,"realp":0.011},{"name":"Scyther","usage":0.12402,"raw":68,"rawp":0.124,"real":6,"realp":0.066},{"name":"Illumise","usage":0.12402,"raw":68,"rawp":0.124,"real":0,"realp":0},{"name":"Persian","usage":0.12402,"raw":68,"rawp":0.124,"real":1,"realp":0.011},{"name":"Granbull","usage":0.12219,"raw":67,"rawp":0.122,"real":6,"realp":0.066},{"name":"Carnivine","usage":0.12219,"raw":67,"rawp":0.122,"real":0,"realp":0},{"name":"Stunfisk","usage":0.12037,"raw":66,"rawp":0.12,"real":41,"realp":0.449},{"name":"Hoppip","usage":0.12037,"raw":66,"rawp":0.12,"real":7,"realp":0.077},{"name":"Teddiursa","usage":0.11854,"raw":65,"rawp":0.119,"real":7,"realp":0.077},{"name":"Fomantis","usage":0.11854,"raw":65,"rawp":0.119,"real":0,"realp":0},{"name":"Bellsprout","usage":0.1149,"raw":63,"rawp":0.115,"real":39,"realp":0.427},{"name":"Whiscash","usage":0.1149,"raw":63,"rawp":0.115,"real":35,"realp":0.383},{"name":"Nihilego","usage":0.1149,"raw":63,"rawp":0.115,"real":34,"realp":0.372},{"name":"Smoochum","usage":0.1149,"raw":63,"rawp":0.115,"real":7,"realp":0.077},{"name":"Magmortar","usage":0.1149,"raw":63,"rawp":0.115,"real":7,"realp":0.077},{"name":"Tepig","usage":0.11307,"raw":62,"rawp":0.113,"real":3,"realp":0.033},{"name":"Alomomola","usage":0.11307,"raw":62,"rawp":0.113,"real":0,"realp":0},{"name":"Makuhita","usage":0.11307,"raw":62,"rawp":0.113,"real":1,"realp":0.011},{"name":"Mankey","usage":0.11125,"raw":61,"rawp":0.111,"real":8,"realp":0.088},{"name":"Goldeen","usage":0.11125,"raw":61,"rawp":0.111,"real":2,"realp":0.022},{"name":"Kingler","usage":0.11125,"raw":61,"rawp":0.111,"real":1,"realp":0.011},{"name":"Floatzel","usage":0.10943,"raw":60,"rawp":0.109,"real":0,"realp":0},{"name":"Aromatisse","usage":0.10943,"raw":60,"rawp":0.109,"real":10,"realp":0.109},{"name":"Slurpuff","usage":0.10943,"raw":60,"rawp":0.109,"real":0,"realp":0},{"name":"Rowlet","usage":0.10943,"raw":60,"rawp":0.109,"real":30,"realp":0.328},{"name":"Golduck","usage":0.1076,"raw":59,"rawp":0.108,"real":0,"realp":0},{"name":"Samurott","usage":0.1076,"raw":59,"rawp":0.108,"real":6,"realp":0.066},{"name":"Vullaby","usage":0.1076,"raw":59,"rawp":0.108,"real":27,"realp":0.295},{"name":"Relicanth","usage":0.10578,"raw":58,"rawp":0.106,"real":4,"realp":0.044},{"name":"Articuno","usage":0.10578,"raw":58,"rawp":0.106,"real":19,"realp":0.208},{"name":"Pumpkaboo","usage":0.10395,"raw":57,"rawp":0.104,"real":23,"realp":0.252},{"name":"Marshtomp","usage":0.10395,"raw":57,"rawp":0.104,"real":47,"realp":0.514},{"name":"Yamask","usage":0.10395,"raw":57,"rawp":0.104,"real":49,"realp":0.536},{"name":"Delphox","usage":0.10395,"raw":57,"rawp":0.104,"real":31,"realp":0.339},{"name":"Sandslash","usage":0.10213,"raw":56,"rawp":0.102,"real":2,"realp":0.022},{"name":"Vaporeon","usage":0.10213,"raw":56,"rawp":0.102,"real":22,"realp":0.241},{"name":"Fraxure","usage":0.10213,"raw":56,"rawp":0.102,"real":11,"realp":0.12},{"name":"Beheeyem","usage":0.10213,"raw":56,"rawp":0.102,"real":1,"realp":0.011},{"name":"Shieldon","usage":0.10213,"raw":56,"rawp":0.102,"real":7,"realp":0.077},{"name":"Buneary","usage":0.10031,"raw":55,"rawp":0.1,"real":11,"realp":0.12},{"name":"Weezing","usage":0.10031,"raw":55,"rawp":0.1,"real":0,"realp":0},{"name":"Metapod","usage":0.10031,"raw":55,"rawp":0.1,"real":6,"realp":0.066},{"name":"Froslass","usage":0.10031,"raw":55,"rawp":0.1,"real":43,"realp":0.47},{"name":"Sneasel","usage":0.10031,"raw":55,"rawp":0.1,"real":11,"realp":0.12},{"name":"Omastar","usage":0.09848,"raw":54,"rawp":0.098,"real":8,"realp":0.088},{"name":"Zorua","usage":0.09848,"raw":54,"rawp":0.098,"real":0,"realp":0},{"name":"Karrablast","usage":0.09848,"raw":54,"rawp":0.098,"real":0,"realp":0},{"name":"Spinarak","usage":0.09848,"raw":54,"rawp":0.098,"real":37,"realp":0.405},{"name":"Pignite","usage":0.09666,"raw":53,"rawp":0.097,"real":45,"realp":0.492},{"name":"Delibird","usage":0.09666,"raw":53,"rawp":0.097,"real":10,"realp":0.109},{"name":"Chinchou","usage":0.09666,"raw":53,"rawp":0.097,"real":36,"realp":0.394},{"name":"Terrakion","usage":0.09666,"raw":53,"rawp":0.097,"real":16,"realp":0.175},{"name":"Vulpix-Alola","usage":0.09484,"raw":52,"rawp":0.095,"real":0,"realp":0},{"name":"Mantine","usage":0.09484,"raw":52,"rawp":0.095,"real":9,"realp":0.098},{"name":"Chespin","usage":0.09484,"raw":52,"rawp":0.095,"real":0,"realp":0},{"name":"Luxray","usage":0.09484,"raw":52,"rawp":0.095,"real":35,"realp":0.383},{"name":"Shinx","usage":0.09484,"raw":52,"rawp":0.095,"real":26,"realp":0.284},{"name":"Mewtwo-Mega-X","usage":0.09301,"raw":51,"rawp":0.093,"real":1,"realp":0.011},{"name":"Turtwig","usage":0.09301,"raw":51,"rawp":0.093,"real":3,"realp":0.033},{"name":"Doduo","usage":0.09119,"raw":50,"rawp":0.091,"real":4,"realp":0.044},{"name":"Solrock","usage":0.09119,"raw":50,"rawp":0.091,"real":18,"realp":0.197},{"name":"Surskit","usage":0.09119,"raw":50,"rawp":0.091,"real":13,"realp":0.142},{"name":"Rotom-Fan","usage":0.09119,"raw":50,"rawp":0.091,"real":26,"realp":0.284},{"name":"Azelf","usage":0.09119,"raw":50,"rawp":0.091,"real":1,"realp":0.011},{"name":"Litleo","usage":0.09119,"raw":50,"rawp":0.091,"real":35,"realp":0.383},{"name":"Lunatone","usage":0.09119,"raw":50,"rawp":0.091,"real":0,"realp":0},{"name":"Leavanny","usage":0.08754,"raw":48,"rawp":0.088,"real":1,"realp":0.011},{"name":"Kricketot","usage":0.08754,"raw":48,"rawp":0.088,"real":2,"realp":0.022},{"name":"Beldum","usage":0.08754,"raw":48,"rawp":0.088,"real":34,"realp":0.372},{"name":"Corphish","usage":0.08754,"raw":48,"rawp":0.088,"real":4,"realp":0.044},{"name":"Manectric","usage":0.08754,"raw":48,"rawp":0.088,"real":14,"realp":0.153},{"name":"Swablu","usage":0.08754,"raw":48,"rawp":0.088,"real":3,"realp":0.033},{"name":"Cobalion","usage":0.08754,"raw":48,"rawp":0.088,"real":19,"realp":0.208},{"name":"Ursaring","usage":0.08754,"raw":48,"rawp":0.088,"real":6,"realp":0.066},{"name":"Yanma","usage":0.08572,"raw":47,"rawp":0.086,"real":9,"realp":0.098},{"name":"Silvally","usage":0.08572,"raw":47,"rawp":0.086,"real":8,"realp":0.088},{"name":"Dragonair","usage":0.08572,"raw":47,"rawp":0.086,"real":8,"realp":0.088},{"name":"Emolga","usage":0.08389,"raw":46,"rawp":0.084,"real":24,"realp":0.263},{"name":"Charizard-Mega-X","usage":0.08389,"raw":46,"rawp":0.084,"real":6,"realp":0.066},{"name":"Charizard-Mega-Y","usage":0.08389,"raw":46,"rawp":0.084,"real":1,"realp":0.011},{"name":"Zangoose","usage":0.08389,"raw":46,"rawp":0.084,"real":15,"realp":0.164},{"name":"Magby","usage":0.08389,"raw":46,"rawp":0.084,"real":7,"realp":0.077},{"name":"Roselia","usage":0.08389,"raw":46,"rawp":0.084,"real":0,"realp":0},{"name":"Starly","usage":0.08207,"raw":45,"rawp":0.082,"real":3,"realp":0.033},{"name":"Piloswine","usage":0.08025,"raw":44,"rawp":0.08,"real":12,"realp":0.131},{"name":"Hakamo-o","usage":0.08025,"raw":44,"rawp":0.08,"real":17,"realp":0.186},{"name":"Croagunk","usage":0.08025,"raw":44,"rawp":0.08,"real":9,"realp":0.098},{"name":"Poliwag","usage":0.07842,"raw":43,"rawp":0.078,"real":7,"realp":0.077},{"name":"Shelmet","usage":0.07842,"raw":43,"rawp":0.078,"real":0,"realp":0},{"name":"Seedot","usage":0.0766,"raw":42,"rawp":0.077,"real":0,"realp":0},{"name":"Vikavolt","usage":0.0766,"raw":42,"rawp":0.077,"real":3,"realp":0.033},{"name":"Lickilicky","usage":0.0766,"raw":42,"rawp":0.077,"real":6,"realp":0.066},{"name":"Skrelp","usage":0.07477,"raw":41,"rawp":0.075,"real":15,"realp":0.164},{"name":"Ampharos","usage":0.07477,"raw":41,"rawp":0.075,"real":11,"realp":0.12},{"name":"Hippopotas","usage":0.07477,"raw":41,"rawp":0.075,"real":0,"realp":0},{"name":"Plusle","usage":0.07477,"raw":41,"rawp":0.075,"real":13,"realp":0.142},{"name":"Voltorb","usage":0.07477,"raw":41,"rawp":0.075,"real":29,"realp":0.317},{"name":"Vanillite","usage":0.07477,"raw":41,"rawp":0.075,"real":4,"realp":0.044},{"name":"Finneon","usage":0.07295,"raw":40,"rawp":0.073,"real":8,"realp":0.088},{"name":"Monferno","usage":0.07295,"raw":40,"rawp":0.073,"real":22,"realp":0.241},{"name":"Rhyhorn","usage":0.07295,"raw":40,"rawp":0.073,"real":8,"realp":0.088},{"name":"Furret","usage":0.07113,"raw":39,"rawp":0.071,"real":18,"realp":0.197},{"name":"Diancie-Mega","usage":0.07113,"raw":39,"rawp":0.071,"real":5,"realp":0.055},{"name":"Mothim","usage":0.07113,"raw":39,"rawp":0.071,"real":2,"realp":0.022},{"name":"Trapinch","usage":0.07113,"raw":39,"rawp":0.071,"real":4,"realp":0.044},{"name":"Onix","usage":0.07113,"raw":39,"rawp":0.071,"real":3,"realp":0.033},{"name":"Mandibuzz","usage":0.0693,"raw":38,"rawp":0.069,"real":13,"realp":0.142},{"name":"Mewtwo-Mega-Y","usage":0.0693,"raw":38,"rawp":0.069,"real":5,"realp":0.055},{"name":"Treecko","usage":0.0693,"raw":38,"rawp":0.069,"real":0,"realp":0},{"name":"Morelull","usage":0.0693,"raw":38,"rawp":0.069,"real":3,"realp":0.033},{"name":"Wurmple","usage":0.0693,"raw":38,"rawp":0.069,"real":3,"realp":0.033},{"name":"Snivy","usage":0.0693,"raw":38,"rawp":0.069,"real":8,"realp":0.088},{"name":"Meowth","usage":0.06748,"raw":37,"rawp":0.067,"real":11,"realp":0.12},{"name":"Alakazam-Mega","usage":0.06748,"raw":37,"rawp":0.067,"real":2,"realp":0.022},{"name":"Lileep","usage":0.06748,"raw":37,"rawp":0.067,"real":34,"realp":0.372},{"name":"Sableye-Mega","usage":0.06748,"raw":37,"rawp":0.067,"real":19,"realp":0.208},{"name":"Mawile-Mega","usage":0.06748,"raw":37,"rawp":0.067,"real":7,"realp":0.077},{"name":"Swalot","usage":0.06748,"raw":37,"rawp":0.067,"real":0,"realp":0},{"name":"Rapidash","usage":0.06748,"raw":37,"rawp":0.067,"real":0,"realp":0},{"name":"Spearow","usage":0.06566,"raw":36,"rawp":0.066,"real":3,"realp":0.033},{"name":"Sandshrew","usage":0.06566,"raw":36,"rawp":0.066,"real":25,"realp":0.274},{"name":"Shellder","usage":0.06566,"raw":36,"rawp":0.066,"real":0,"realp":0},{"name":"Golett","usage":0.06566,"raw":36,"rawp":0.066,"real":35,"realp":0.383},{"name":"Goomy","usage":0.06566,"raw":36,"rawp":0.066,"real":13,"realp":0.142},{"name":"Pikipek","usage":0.06566,"raw":36,"rawp":0.066,"real":0,"realp":0},{"name":"Scizor-Mega","usage":0.06383,"raw":35,"rawp":0.064,"real":23,"realp":0.252},{"name":"Minccino","usage":0.06383,"raw":35,"rawp":0.064,"real":1,"realp":0.011},{"name":"Poipole","usage":0.06383,"raw":35,"rawp":0.064,"real":5,"realp":0.055},{"name":"Carvanha","usage":0.06383,"raw":35,"rawp":0.064,"real":5,"realp":0.055},{"name":"Rhydon","usage":0.06383,"raw":35,"rawp":0.064,"real":1,"realp":0.011},{"name":"Clauncher","usage":0.06383,"raw":35,"rawp":0.064,"real":0,"realp":0},{"name":"Roggenrola","usage":0.06201,"raw":34,"rawp":0.062,"real":10,"realp":0.109},{"name":"Parasect","usage":0.06201,"raw":34,"rawp":0.062,"real":1,"realp":0.011},{"name":"Ducklett","usage":0.06201,"raw":34,"rawp":0.062,"real":12,"realp":0.131},{"name":"Koffing","usage":0.06201,"raw":34,"rawp":0.062,"real":0,"realp":0},{"name":"Sandile","usage":0.06201,"raw":34,"rawp":0.062,"real":10,"realp":0.109},{"name":"Palpitoad","usage":0.06201,"raw":34,"rawp":0.062,"real":32,"realp":0.35},{"name":"Lickitung","usage":0.06201,"raw":34,"rawp":0.062,"real":25,"realp":0.274},{"name":"Type: Null","usage":0.06018,"raw":33,"rawp":0.06,"real":15,"realp":0.164},{"name":"Spheal","usage":0.06018,"raw":33,"rawp":0.06,"real":18,"realp":0.197},{"name":"Glaceon","usage":0.06018,"raw":33,"rawp":0.06,"real":2,"realp":0.022},{"name":"Pidove","usage":0.05836,"raw":32,"rawp":0.058,"real":26,"realp":0.284},{"name":"Sentret","usage":0.05836,"raw":32,"rawp":0.058,"real":12,"realp":0.131},{"name":"Luvdisc","usage":0.05836,"raw":32,"rawp":0.058,"real":2,"realp":0.022},{"name":"Leafeon","usage":0.05836,"raw":32,"rawp":0.058,"real":5,"realp":0.055},{"name":"Popplio","usage":0.05836,"raw":32,"rawp":0.058,"real":3,"realp":0.033},{"name":"Dugtrio-Alola","usage":0.05836,"raw":32,"rawp":0.058,"real":16,"realp":0.175},{"name":"Torchic","usage":0.05836,"raw":32,"rawp":0.058,"real":13,"realp":0.142},{"name":"Dwebble","usage":0.05654,"raw":31,"rawp":0.057,"real":8,"realp":0.088},{"name":"Seaking","usage":0.05654,"raw":31,"rawp":0.057,"real":0,"realp":0},{"name":"Amoonguss","usage":0.05654,"raw":31,"rawp":0.057,"real":10,"realp":0.109},{"name":"Lairon","usage":0.05654,"raw":31,"rawp":0.057,"real":13,"realp":0.142},{"name":"Rufflet","usage":0.05471,"raw":30,"rawp":0.055,"real":10,"realp":0.109},{"name":"Lopunny-Mega","usage":0.05471,"raw":30,"rawp":0.055,"real":3,"realp":0.033},{"name":"Lampent","usage":0.05471,"raw":30,"rawp":0.055,"real":10,"realp":0.109},{"name":"Meditite","usage":0.05471,"raw":30,"rawp":0.055,"real":25,"realp":0.274},{"name":"Combusken","usage":0.05471,"raw":30,"rawp":0.055,"real":4,"realp":0.044},{"name":"Tirtouga","usage":0.05471,"raw":30,"rawp":0.055,"real":9,"realp":0.098},{"name":"Shellos","usage":0.05289,"raw":29,"rawp":0.053,"real":0,"realp":0},{"name":"Mareanie","usage":0.05289,"raw":29,"rawp":0.053,"real":0,"realp":0},{"name":"Joltik","usage":0.05289,"raw":29,"rawp":0.053,"real":23,"realp":0.252},{"name":"Pidgeot","usage":0.05289,"raw":29,"rawp":0.053,"real":8,"realp":0.088},{"name":"Swampert-Mega","usage":0.05107,"raw":28,"rawp":0.051,"real":12,"realp":0.131},{"name":"Pikachu-Original","usage":0.05107,"raw":28,"rawp":0.051,"real":11,"realp":0.12},{"name":"Gible","usage":0.05107,"raw":28,"rawp":0.051,"real":16,"realp":0.175},{"name":"Bagon","usage":0.05107,"raw":28,"rawp":0.051,"real":2,"realp":0.022},{"name":"Baltoy","usage":0.04924,"raw":27,"rawp":0.049,"real":12,"realp":0.131},{"name":"Paras","usage":0.04924,"raw":27,"rawp":0.049,"real":0,"realp":0},{"name":"Oranguru","usage":0.04924,"raw":27,"rawp":0.049,"real":15,"realp":0.164},{"name":"Throh","usage":0.04924,"raw":27,"rawp":0.049,"real":0,"realp":0},{"name":"Poochyena","usage":0.04924,"raw":27,"rawp":0.049,"real":23,"realp":0.252},{"name":"Gorebyss","usage":0.04924,"raw":27,"rawp":0.049,"real":0,"realp":0},{"name":"Gourgeist-Large","usage":0.04924,"raw":27,"rawp":0.049,"real":0,"realp":0},{"name":"Graveler","usage":0.04924,"raw":27,"rawp":0.049,"real":0,"realp":0},{"name":"Kabutops","usage":0.04742,"raw":26,"rawp":0.047,"real":3,"realp":0.033},{"name":"Ariados","usage":0.04742,"raw":26,"rawp":0.047,"real":5,"realp":0.055},{"name":"Chimchar","usage":0.04742,"raw":26,"rawp":0.047,"real":6,"realp":0.066},{"name":"Servine","usage":0.04742,"raw":26,"rawp":0.047,"real":0,"realp":0},{"name":"Wailmer","usage":0.04742,"raw":26,"rawp":0.047,"real":4,"realp":0.044},{"name":"Dewott","usage":0.04742,"raw":26,"rawp":0.047,"real":7,"realp":0.077},{"name":"Vibrava","usage":0.04742,"raw":26,"rawp":0.047,"real":0,"realp":0},{"name":"Arceus-Grass","usage":0.04742,"raw":26,"rawp":0.047,"real":0,"realp":0},{"name":"Cubone","usage":0.04742,"raw":26,"rawp":0.047,"real":4,"realp":0.044},{"name":"Grimer","usage":0.04559,"raw":25,"rawp":0.046,"real":3,"realp":0.033},{"name":"Ledian","usage":0.04377,"raw":24,"rawp":0.044,"real":0,"realp":0},{"name":"Golbat","usage":0.04377,"raw":24,"rawp":0.044,"real":5,"realp":0.055},{"name":"Jangmo-o","usage":0.04377,"raw":24,"rawp":0.044,"real":5,"realp":0.055},{"name":"Horsea","usage":0.04377,"raw":24,"rawp":0.044,"real":17,"realp":0.186},{"name":"Cacnea","usage":0.04377,"raw":24,"rawp":0.044,"real":0,"realp":0},{"name":"Swanna","usage":0.04195,"raw":23,"rawp":0.042,"real":1,"realp":0.011},{"name":"Virizion","usage":0.04195,"raw":23,"rawp":0.042,"real":8,"realp":0.088},{"name":"Dartrix","usage":0.04195,"raw":23,"rawp":0.042,"real":17,"realp":0.186},{"name":"Cutiefly","usage":0.04195,"raw":23,"rawp":0.042,"real":0,"realp":0},{"name":"Lycanroc-Midnight","usage":0.04195,"raw":23,"rawp":0.042,"real":0,"realp":0},{"name":"Qwilfish","usage":0.04195,"raw":23,"rawp":0.042,"real":9,"realp":0.098},{"name":"Kyurem","usage":0.04195,"raw":23,"rawp":0.042,"real":6,"realp":0.066},{"name":"Oricorio-Pa'u","usage":0.04195,"raw":23,"rawp":0.042,"real":5,"realp":0.055},{"name":"Blitzle","usage":0.04195,"raw":23,"rawp":0.042,"real":9,"realp":0.098},{"name":"Duosion","usage":0.04012,"raw":22,"rawp":0.04,"real":2,"realp":0.022},{"name":"Mareep","usage":0.04012,"raw":22,"rawp":0.04,"real":16,"realp":0.175},{"name":"Litten","usage":0.04012,"raw":22,"rawp":0.04,"real":0,"realp":0},{"name":"Seadra","usage":0.04012,"raw":22,"rawp":0.04,"real":3,"realp":0.033},{"name":"Trubbish","usage":0.04012,"raw":22,"rawp":0.04,"real":11,"realp":0.12},{"name":"Omanyte","usage":0.04012,"raw":22,"rawp":0.04,"real":6,"realp":0.066},{"name":"Growlithe","usage":0.04012,"raw":22,"rawp":0.04,"real":3,"realp":0.033},{"name":"Deino","usage":0.0383,"raw":21,"rawp":0.038,"real":0,"realp":0},{"name":"Gengar-Mega","usage":0.0383,"raw":21,"rawp":0.038,"real":16,"realp":0.175},{"name":"Hoothoot","usage":0.0383,"raw":21,"rawp":0.038,"real":6,"realp":0.066},{"name":"Tyrogue","usage":0.0383,"raw":21,"rawp":0.038,"real":14,"realp":0.153},{"name":"Machoke","usage":0.0383,"raw":21,"rawp":0.038,"real":13,"realp":0.142},{"name":"Grumpig","usage":0.0383,"raw":21,"rawp":0.038,"real":3,"realp":0.033},{"name":"Crabrawler","usage":0.0383,"raw":21,"rawp":0.038,"real":10,"realp":0.109},{"name":"Grovyle","usage":0.0383,"raw":21,"rawp":0.038,"real":0,"realp":0},{"name":"Scatterbug","usage":0.0383,"raw":21,"rawp":0.038,"real":0,"realp":0},{"name":"Noctowl","usage":0.0383,"raw":21,"rawp":0.038,"real":7,"realp":0.077},{"name":"Muk","usage":0.0383,"raw":21,"rawp":0.038,"real":0,"realp":0},{"name":"Seviper","usage":0.03648,"raw":20,"rawp":0.036,"real":0,"realp":0},{"name":"Wormadam","usage":0.03648,"raw":20,"rawp":0.036,"real":0,"realp":0},{"name":"Poliwhirl","usage":0.03648,"raw":20,"rawp":0.036,"real":0,"realp":0},{"name":"Meowth-Alola","usage":0.03648,"raw":20,"rawp":0.036,"real":0,"realp":0},{"name":"Tentacool","usage":0.03648,"raw":20,"rawp":0.036,"real":1,"realp":0.011},{"name":"Nuzleaf","usage":0.03648,"raw":20,"rawp":0.036,"real":8,"realp":0.088},{"name":"Mimikyu-Totem","usage":0.03465,"raw":19,"rawp":0.035,"real":11,"realp":0.12},{"name":"Archen","usage":0.03465,"raw":19,"rawp":0.035,"real":5,"realp":0.055},{"name":"Whismur","usage":0.03465,"raw":19,"rawp":0.035,"real":6,"realp":0.066},{"name":"Ivysaur","usage":0.03465,"raw":19,"rawp":0.035,"real":0,"realp":0},{"name":"Scraggy","usage":0.03465,"raw":19,"rawp":0.035,"real":7,"realp":0.077},{"name":"Flaaffy","usage":0.03465,"raw":19,"rawp":0.035,"real":11,"realp":0.12},{"name":"Garbodor","usage":0.03465,"raw":19,"rawp":0.035,"real":3,"realp":0.033},{"name":"Drilbur","usage":0.03465,"raw":19,"rawp":0.035,"real":4,"realp":0.044},{"name":"Lucario-Mega","usage":0.03465,"raw":19,"rawp":0.035,"real":7,"realp":0.077},{"name":"Cranidos","usage":0.03465,"raw":19,"rawp":0.035,"real":0,"realp":0},{"name":"Rotom-Mow","usage":0.03283,"raw":18,"rawp":0.033,"real":3,"realp":0.033},{"name":"Galvantula","usage":0.03283,"raw":18,"rawp":0.033,"real":1,"realp":0.011},{"name":"Eelektrik","usage":0.03283,"raw":18,"rawp":0.033,"real":10,"realp":0.109},{"name":"Braviary","usage":0.03283,"raw":18,"rawp":0.033,"real":5,"realp":0.055},{"name":"Larvitar","usage":0.03283,"raw":18,"rawp":0.033,"real":2,"realp":0.022},{"name":"Purugly","usage":0.03283,"raw":18,"rawp":0.033,"real":3,"realp":0.033},{"name":"Tauros","usage":0.03283,"raw":18,"rawp":0.033,"real":1,"realp":0.011},{"name":"Tyrantrum","usage":0.03283,"raw":18,"rawp":0.033,"real":4,"realp":0.044},{"name":"Nidorina","usage":0.03283,"raw":18,"rawp":0.033,"real":0,"realp":0},{"name":"Mantyke","usage":0.031,"raw":17,"rawp":0.031,"real":8,"realp":0.088},{"name":"Snorunt","usage":0.031,"raw":17,"rawp":0.031,"real":1,"realp":0.011},{"name":"NidoranF","usage":0.031,"raw":17,"rawp":0.031,"real":0,"realp":0},{"name":"Phanpy","usage":0.031,"raw":17,"rawp":0.031,"real":4,"realp":0.044},{"name":"Glalie","usage":0.031,"raw":17,"rawp":0.031,"real":9,"realp":0.098},{"name":"Florges","usage":0.031,"raw":17,"rawp":0.031,"real":1,"realp":0.011},{"name":"Cascoon","usage":0.031,"raw":17,"rawp":0.031,"real":0,"realp":0},{"name":"Wartortle","usage":0.031,"raw":17,"rawp":0.031,"real":2,"realp":0.022},{"name":"Ponyta","usage":0.031,"raw":17,"rawp":0.031,"real":13,"realp":0.142},{"name":"Charmeleon","usage":0.031,"raw":17,"rawp":0.031,"real":1,"realp":0.011},{"name":"Venusaur-Mega","usage":0.031,"raw":17,"rawp":0.031,"real":1,"realp":0.011},{"name":"Venipede","usage":0.02918,"raw":16,"rawp":0.029,"real":2,"realp":0.022},{"name":"Bronzor","usage":0.02918,"raw":16,"rawp":0.029,"real":12,"realp":0.131},{"name":"Fearow","usage":0.02918,"raw":16,"rawp":0.029,"real":0,"realp":0},{"name":"Skiploom","usage":0.02736,"raw":15,"rawp":0.027,"real":2,"realp":0.022},{"name":"Watchog","usage":0.02736,"raw":15,"rawp":0.027,"real":0,"realp":0},{"name":"Gothitelle","usage":0.02736,"raw":15,"rawp":0.027,"real":0,"realp":0},{"name":"Stantler","usage":0.02736,"raw":15,"rawp":0.027,"real":3,"realp":0.033},{"name":"Beartic","usage":0.02736,"raw":15,"rawp":0.027,"real":0,"realp":0},{"name":"Krokorok","usage":0.02736,"raw":15,"rawp":0.027,"real":0,"realp":0},{"name":"Tyranitar-Mega","usage":0.02553,"raw":14,"rawp":0.026,"real":2,"realp":0.022},{"name":"Gardevoir-Mega","usage":0.02553,"raw":14,"rawp":0.026,"real":1,"realp":0.011},{"name":"Mightyena","usage":0.02553,"raw":14,"rawp":0.026,"real":2,"realp":0.022},{"name":"Hippowdon","usage":0.02553,"raw":14,"rawp":0.026,"real":2,"realp":0.022},{"name":"Unfezant","usage":0.02553,"raw":14,"rawp":0.026,"real":10,"realp":0.109},{"name":"Frogadier","usage":0.02371,"raw":13,"rawp":0.024,"real":0,"realp":0},{"name":"Electabuzz","usage":0.02371,"raw":13,"rawp":0.024,"real":10,"realp":0.109},{"name":"Cherubi","usage":0.02371,"raw":13,"rawp":0.024,"real":0,"realp":0},{"name":"Bunnelby","usage":0.02371,"raw":13,"rawp":0.024,"real":4,"realp":0.044},{"name":"Sunflora","usage":0.02371,"raw":13,"rawp":0.024,"real":1,"realp":0.011},{"name":"Musharna","usage":0.02371,"raw":13,"rawp":0.024,"real":0,"realp":0},{"name":"Combee","usage":0.02371,"raw":13,"rawp":0.024,"real":6,"realp":0.066},{"name":"Herdier","usage":0.02371,"raw":13,"rawp":0.024,"real":2,"realp":0.022},{"name":"Meganium","usage":0.02371,"raw":13,"rawp":0.024,"real":0,"realp":0},{"name":"Anorith","usage":0.02371,"raw":13,"rawp":0.024,"real":11,"realp":0.12},{"name":"Krabby","usage":0.02371,"raw":13,"rawp":0.024,"real":1,"realp":0.011},{"name":"Ledyba","usage":0.02371,"raw":13,"rawp":0.024,"real":6,"realp":0.066},{"name":"Snubbull","usage":0.02189,"raw":12,"rawp":0.022,"real":0,"realp":0},{"name":"Walrein","usage":0.02189,"raw":12,"rawp":0.022,"real":6,"realp":0.066},{"name":"Budew","usage":0.02189,"raw":12,"rawp":0.022,"real":10,"realp":0.109},{"name":"Quilava","usage":0.02189,"raw":12,"rawp":0.022,"real":2,"realp":0.022},{"name":"Floette","usage":0.02189,"raw":12,"rawp":0.022,"real":10,"realp":0.109},{"name":"Pumpkaboo-Small","usage":0.02189,"raw":12,"rawp":0.022,"real":12,"realp":0.131},{"name":"Drowzee","usage":0.02189,"raw":12,"rawp":0.022,"real":0,"realp":0},{"name":"Araquanid-Totem","usage":0.02189,"raw":12,"rawp":0.022,"real":0,"realp":0},{"name":"Salamence-Mega","usage":0.02189,"raw":12,"rawp":0.022,"real":2,"realp":0.022},{"name":"Torracat","usage":0.02006,"raw":11,"rawp":0.02,"real":6,"realp":0.066},{"name":"Huntail","usage":0.02006,"raw":11,"rawp":0.02,"real":0,"realp":0},{"name":"Quilladin","usage":0.02006,"raw":11,"rawp":0.02,"real":0,"realp":0},{"name":"Elekid","usage":0.01824,"raw":10,"rawp":0.018,"real":4,"realp":0.044},{"name":"Cubchoo","usage":0.01824,"raw":10,"rawp":0.018,"real":1,"realp":0.011},{"name":"Snover","usage":0.01824,"raw":10,"rawp":0.018,"real":8,"realp":0.088},{"name":"Latias-Mega","usage":0.01824,"raw":10,"rawp":0.018,"real":0,"realp":0},{"name":"Gyarados-Mega","usage":0.01824,"raw":10,"rawp":0.018,"real":3,"realp":0.033},{"name":"Nidorino","usage":0.01824,"raw":10,"rawp":0.018,"real":0,"realp":0},{"name":"Wimpod","usage":0.01641,"raw":9,"rawp":0.016,"real":3,"realp":0.033},{"name":"Dustox","usage":0.01641,"raw":9,"rawp":0.016,"real":0,"realp":0},{"name":"Electrike","usage":0.01641,"raw":9,"rawp":0.016,"real":6,"realp":0.066},{"name":"Silcoon","usage":0.01641,"raw":9,"rawp":0.016,"real":0,"realp":0},{"name":"Pumpkaboo-Super","usage":0.01641,"raw":9,"rawp":0.016,"real":3,"realp":0.033},{"name":"Kangaskhan-Mega","usage":0.01641,"raw":9,"rawp":0.016,"real":4,"realp":0.044},{"name":"Loudred","usage":0.01641,"raw":9,"rawp":0.016,"real":0,"realp":0},{"name":"Aerodactyl-Mega","usage":0.01641,"raw":9,"rawp":0.016,"real":4,"realp":0.044},{"name":"Aggron-Mega","usage":0.01459,"raw":8,"rawp":0.015,"real":3,"realp":0.033},{"name":"Trumbeak","usage":0.01459,"raw":8,"rawp":0.015,"real":1,"realp":0.011},{"name":"Wingull","usage":0.01459,"raw":8,"rawp":0.015,"real":8,"realp":0.088},{"name":"Silvally-Steel","usage":0.01459,"raw":8,"rawp":0.015,"real":0,"realp":0},{"name":"Uxie","usage":0.01459,"raw":8,"rawp":0.015,"real":0,"realp":0},{"name":"Noibat","usage":0.01459,"raw":8,"rawp":0.015,"real":1,"realp":0.011},{"name":"Gallade-Mega","usage":0.01459,"raw":8,"rawp":0.015,"real":2,"realp":0.022},{"name":"Luxio","usage":0.01459,"raw":8,"rawp":0.015,"real":8,"realp":0.088},{"name":"Beedrill-Mega","usage":0.01277,"raw":7,"rawp":0.013,"real":1,"realp":0.011},{"name":"Swirlix","usage":0.01277,"raw":7,"rawp":0.013,"real":2,"realp":0.022},{"name":"Whirlipede","usage":0.01277,"raw":7,"rawp":0.013,"real":0,"realp":0},{"name":"NidoranM","usage":0.01277,"raw":7,"rawp":0.013,"real":1,"realp":0.011},{"name":"Skiddo","usage":0.01277,"raw":7,"rawp":0.013,"real":1,"realp":0.011},{"name":"Tympole","usage":0.01277,"raw":7,"rawp":0.013,"real":2,"realp":0.022},{"name":"Banette-Mega","usage":0.01277,"raw":7,"rawp":0.013,"real":3,"realp":0.033},{"name":"Buizel","usage":0.01277,"raw":7,"rawp":0.013,"real":1,"realp":0.011},{"name":"Lombre","usage":0.01277,"raw":7,"rawp":0.013,"real":4,"realp":0.044},{"name":"Skorupi","usage":0.01277,"raw":7,"rawp":0.013,"real":7,"realp":0.077},{"name":"Gothita","usage":0.01277,"raw":7,"rawp":0.013,"real":3,"realp":0.033},{"name":"Kabuto","usage":0.01277,"raw":7,"rawp":0.013,"real":6,"realp":0.066},{"name":"Munna","usage":0.01277,"raw":7,"rawp":0.013,"real":0,"realp":0},{"name":"Silvally-Ghost","usage":0.01277,"raw":7,"rawp":0.013,"real":2,"realp":0.022},{"name":"Silvally-Dragon","usage":0.01277,"raw":7,"rawp":0.013,"real":0,"realp":0},{"name":"Pinsir-Mega","usage":0.01277,"raw":7,"rawp":0.013,"real":0,"realp":0},{"name":"Mienfoo","usage":0.01277,"raw":7,"rawp":0.013,"real":1,"realp":0.011},{"name":"Patrat","usage":0.01277,"raw":7,"rawp":0.013,"real":5,"realp":0.055},{"name":"Klang","usage":0.01094,"raw":6,"rawp":0.011,"real":6,"realp":0.066},{"name":"Kirlia","usage":0.01094,"raw":6,"rawp":0.011,"real":1,"realp":0.011},{"name":"Weepinbell","usage":0.01094,"raw":6,"rawp":0.011,"real":1,"realp":0.011},{"name":"Heracross-Mega","usage":0.01094,"raw":6,"rawp":0.011,"real":0,"realp":0},{"name":"Wormadam-Sandy","usage":0.01094,"raw":6,"rawp":0.011,"real":0,"realp":0},{"name":"Blastoise-Mega","usage":0.01094,"raw":6,"rawp":0.011,"real":1,"realp":0.011},{"name":"Boldore","usage":0.01094,"raw":6,"rawp":0.011,"real":0,"realp":0},{"name":"Vigoroth","usage":0.01094,"raw":6,"rawp":0.011,"real":3,"realp":0.033},{"name":"Silvally-Bug","usage":0.01094,"raw":6,"rawp":0.011,"real":0,"realp":0},{"name":"Gurdurr","usage":0.01094,"raw":6,"rawp":0.011,"real":0,"realp":0},{"name":"Nincada","usage":0.01094,"raw":6,"rawp":0.011,"real":3,"realp":0.033},{"name":"Wynaut","usage":0.01094,"raw":6,"rawp":0.011,"real":3,"realp":0.033},{"name":"Gabite","usage":0.01094,"raw":6,"rawp":0.011,"real":1,"realp":0.011},{"name":"Lillipup","usage":0.00912,"raw":5,"rawp":0.009,"real":2,"realp":0.022},{"name":"Garchomp-Mega","usage":0.00912,"raw":5,"rawp":0.009,"real":4,"realp":0.044},{"name":"Camerupt-Mega","usage":0.00912,"raw":5,"rawp":0.009,"real":3,"realp":0.033},{"name":"Mudbray","usage":0.00912,"raw":5,"rawp":0.009,"real":0,"realp":0},{"name":"Altaria-Mega","usage":0.00912,"raw":5,"rawp":0.009,"real":3,"realp":0.033},{"name":"Gloom","usage":0.00912,"raw":5,"rawp":0.009,"real":0,"realp":0},{"name":"Pidgeot-Mega","usage":0.00912,"raw":5,"rawp":0.009,"real":4,"realp":0.044},{"name":"Passimian","usage":0.00912,"raw":5,"rawp":0.009,"real":0,"realp":0},{"name":"Pikachu-Sinnoh","usage":0.0073,"raw":4,"rawp":0.007,"real":3,"realp":0.033},{"name":"Gothorita","usage":0.0073,"raw":4,"rawp":0.007,"real":0,"realp":0},{"name":"Pikachu-Alola","usage":0.0073,"raw":4,"rawp":0.007,"real":4,"realp":0.044},{"name":"Larvesta","usage":0.0073,"raw":4,"rawp":0.007,"real":3,"realp":0.033},{"name":"Gulpin","usage":0.0073,"raw":4,"rawp":0.007,"real":1,"realp":0.011},{"name":"Mesprit","usage":0.0073,"raw":4,"rawp":0.007,"real":0,"realp":0},{"name":"Charjabug","usage":0.0073,"raw":4,"rawp":0.007,"real":2,"realp":0.022},{"name":"Lumineon","usage":0.0073,"raw":4,"rawp":0.007,"real":4,"realp":0.044},{"name":"Kakuna","usage":0.0073,"raw":4,"rawp":0.007,"real":3,"realp":0.033},{"name":"Braixen","usage":0.0073,"raw":4,"rawp":0.007,"real":2,"realp":0.022},{"name":"Pikachu-Unova","usage":0.0073,"raw":4,"rawp":0.007,"real":0,"realp":0},{"name":"Vanilluxe","usage":0.0073,"raw":4,"rawp":0.007,"real":0,"realp":0},{"name":"Swadloon","usage":0.0073,"raw":4,"rawp":0.007,"real":0,"realp":0},{"name":"Croconaw","usage":0.0073,"raw":4,"rawp":0.007,"real":1,"realp":0.011},{"name":"Ampharos-Mega","usage":0.0073,"raw":4,"rawp":0.007,"real":0,"realp":0},{"name":"Beautifly","usage":0.0073,"raw":4,"rawp":0.007,"real":0,"realp":0},{"name":"Metang","usage":0.0073,"raw":4,"rawp":0.007,"real":0,"realp":0},{"name":"Salazzle-Totem","usage":0.0073,"raw":4,"rawp":0.007,"real":4,"realp":0.044},{"name":"Vanillish","usage":0.00547,"raw":3,"rawp":0.005,"real":3,"realp":0.033},{"name":"Togedemaru-Totem","usage":0.00547,"raw":3,"rawp":0.005,"real":0,"realp":0},{"name":"Staravia","usage":0.00547,"raw":3,"rawp":0.005,"real":1,"realp":0.011},{"name":"Vikavolt-Totem","usage":0.00547,"raw":3,"rawp":0.005,"real":0,"realp":0},{"name":"Slowbro-Mega","usage":0.00547,"raw":3,"rawp":0.005,"real":0,"realp":0},{"name":"Shelgon","usage":0.00547,"raw":3,"rawp":0.005,"real":0,"realp":0},{"name":"Brionne","usage":0.00547,"raw":3,"rawp":0.005,"real":0,"realp":0},{"name":"Simisear","usage":0.00547,"raw":3,"rawp":0.005,"real":0,"realp":0},{"name":"Espurr","usage":0.00547,"raw":3,"rawp":0.005,"real":0,"realp":0},{"name":"Silvally-Ground","usage":0.00547,"raw":3,"rawp":0.005,"real":1,"realp":0.011},{"name":"Flabebe","usage":0.00547,"raw":3,"rawp":0.005,"real":3,"realp":0.033},{"name":"Pansear","usage":0.00365,"raw":2,"rawp":0.004,"real":0,"realp":0},{"name":"Sealeo","usage":0.00365,"raw":2,"rawp":0.004,"real":2,"realp":0.022},{"name":"Grubbin","usage":0.00365,"raw":2,"rawp":0.004,"real":1,"realp":0.011},{"name":"Pidgeotto","usage":0.00365,"raw":2,"rawp":0.004,"real":0,"realp":0},{"name":"Silvally-Fairy","usage":0.00365,"raw":2,"rawp":0.004,"real":1,"realp":0.011},{"name":"Bayleef","usage":0.00365,"raw":2,"rawp":0.004,"real":0,"realp":0},{"name":"Abomasnow-Mega","usage":0.00365,"raw":2,"rawp":0.004,"real":1,"realp":0.011},{"name":"Rockruff","usage":0.00365,"raw":2,"rawp":0.004,"real":0,"realp":0},{"name":"Magmar","usage":0.00365,"raw":2,"rawp":0.004,"real":0,"realp":0},{"name":"Silvally-Electric","usage":0.00365,"raw":2,"rawp":0.004,"real":1,"realp":0.011},{"name":"Pikachu-Hoenn","usage":0.00365,"raw":2,"rawp":0.004,"real":2,"realp":0.022},{"name":"Tranquill","usage":0.00365,"raw":2,"rawp":0.004,"real":0,"realp":0},{"name":"Burmy","usage":0.00365,"raw":2,"rawp":0.004,"real":0,"realp":0},{"name":"Cherrim","usage":0.00182,"raw":1,"rawp":0.002,"real":1,"realp":0.011},{"name":"Houndoom-Mega","usage":0.00182,"raw":1,"rawp":0.002,"real":1,"realp":0.011},{"name":"Simipour","usage":0.00182,"raw":1,"rawp":0.002,"real":0,"realp":0},{"name":"Sceptile-Mega","usage":0.00182,"raw":1,"rawp":0.002,"real":0,"realp":0},{"name":"Latios-Mega","usage":0.00182,"raw":1,"rawp":0.002,"real":0,"realp":0},{"name":"Steenee","usage":0.00182,"raw":1,"rawp":0.002,"real":1,"realp":0.011},{"name":"Silvally-Psychic","usage":0.00182,"raw":1,"rawp":0.002,"real":0,"realp":0},{"name":"Prinplup","usage":0.00182,"raw":1,"rawp":0.002,"real":1,"realp":0.011},{"name":"Foongus","usage":0.00182,"raw":1,"rawp":0.002,"real":0,"realp":0},{"name":"Blaziken-Mega","usage":0.00182,"raw":1,"rawp":0.002,"real":0,"realp":0},{"name":"Metagross-Mega","usage":0.00182,"raw":1,"rawp":0.002,"real":0,"realp":0},{"name":"Panpour","usage":0.00182,"raw":1,"rawp":0.002,"real":0,"realp":0},{"name":"Audino-Mega","usage":0.00182,"raw":1,"rawp":0.002,"real":1,"realp":0.011},{"name":"Silvally-Dark","usage":0.00182,"raw":1,"rawp":0.002,"real":0,"realp":0},{"name":"Dugtrio","usage":0.00182,"raw":1,"rawp":0.002,"real":1,"realp":0.011},{"name":"Zweilous","usage":0.00182,"raw":1,"rawp":0.002,"real":0,"realp":0},{"name":"Fennekin","usage":0.00182,"raw":1,"rawp":0.002,"real":1,"realp":0.011},{"name":"Silvally-Poison","usage":0.00182,"raw":1,"rawp":0.002,"real":0,"realp":0},{"name":"Glalie-Mega","usage":0.00182,"raw":1,"rawp":0.002,"real":0,"realp":0},{"name":"Silvally-Grass","usage":0.00182,"raw":1,"rawp":0.002,"real":0,"realp":0}]}