{"battles":35,"avg":0.014,"pokemon":[{"name":"Cranidos","usage":59.00928,"raw":18,"rawp":25.714,"real":13,"realp":26.087},{"name":"Abra","usage":46.17015,"raw":17,"rawp":24.286,"real":11,"realp":22.074},{"name":"Ferroseed","usage":34.16414,"raw":9,"rawp":12.857,"real":7,"realp":14.047},{"name":"Meditite","usage":32.70361,"raw":5,"rawp":7.143,"real":4,"realp":8.027},{"name":"Mienfoo","usage":29.467,"raw":15,"rawp":21.429,"real":12,"realp":24.08},{"name":"Doduo","usage":28.9349,"raw":5,"rawp":7.143,"real":2,"realp":4.013},{"name":"Cubone","usage":27.87917,"raw":15,"rawp":21.429,"real":10,"realp":20.067},{"name":"Grimer-Alola","usage":26.1579,"raw":4,"rawp":5.714,"real":3,"realp":6.02},{"name":"Groudon-Primal","usage":25.56771,"raw":9,"rawp":12.857,"real":7,"realp":14.047},{"name":"Hippopotas","usage":24.68247,"raw":9,"rawp":12.857,"real":7,"realp":14.047},{"name":"Gastly","usage":24.03216,"raw":13,"rawp":18.571,"real":7,"realp":14.047},{"name":"Mantyke","usage":22.63123,"raw":4,"rawp":5.714,"real":4,"realp":8.027},{"name":"Pawniard","usage":21.48793,"raw":6,"rawp":8.571,"real":6,"realp":12.04},{"name":"Spritzee","usage":17.65398,"raw":14,"rawp":20,"real":9,"realp":18.06},{"name":"Arceus-Water","usage":14.9311,"raw":1,"rawp":1.429,"real":1,"realp":2.007},{"name":"Vibrava","usage":14.0045,"raw":10,"rawp":14.286,"real":6,"realp":12.04},{"name":"Shroomish","usage":14.0038,"raw":4,"rawp":5.714,"real":4,"realp":8.027},{"name":"Salandit","usage":14.0038,"raw":4,"rawp":5.714,"real":2,"realp":4.013},{"name":"Smeargle","usage":13.87537,"raw":14,"rawp":20,"real":13,"realp":26.087},{"name":"Froakie","usage":13.87537,"raw":10,"rawp":14.286,"real":8,"realp":16.054},{"name":"Staravia","usage":11.85906,"raw":12,"rawp":17.143,"real":11,"realp":22.074},{"name":"Staryu","usage":10.79211,"raw":3,"rawp":4.286,"real":3,"realp":6.02},{"name":"Swirlix","usage":10.72801,"raw":5,"rawp":7.143,"real":3,"realp":6.02},{"name":"Skrelp","usage":10.70683,"raw":1,"rawp":1.429,"real":1,"realp":2.007},{"name":"Sandygast","usage":10.70683,"raw":2,"rawp":2.857,"real":1,"realp":2.007},{"name":"Magnemite","usage":10.53028,"raw":4,"rawp":5.714,"real":4,"realp":8.027},{"name":"Zorua","usage":10.21348,"raw":3,"rawp":4.286,"real":2,"realp":4.013},{"name":"Houndour","usage":10.07255,"raw":2,"rawp":2.857,"real":1,"realp":2.007},{"name":"Clamperl","usage":1.30884,"raw":5,"rawp":7.143,"real":3,"realp":6.02},{"name":"Clefairy","usage":1.13631,"raw":6,"rawp":8.571,"real":4,"realp":8.027},{"name":"Growlithe","usage":0.66225,"raw":9,"rawp":12.857,"real":6,"realp":12.04},{"name":"Honedge","usage":0.59011,"raw":3,"rawp":4.286,"real":3,"realp":6.02},{"name":"Kyurem-White","usage":0.5488,"raw":3,"rawp":4.286,"real":1,"realp":2.007},{"name":"Pikachu","usage":0.5488,"raw":4,"rawp":5.714,"real":3,"realp":6.02},{"name":"Numel","usage":0.5488,"raw":2,"rawp":2.857,"real":1,"realp":2.007},{"name":"Geodude","usage":0.51997,"raw":2,"rawp":2.857,"real":2,"realp":4.013},{"name":"Arceus-Poison","usage":0.51997,"raw":2,"rawp":2.857,"real":0,"realp":0},{"name":"Snover","usage":0.51997,"raw":2,"rawp":2.857,"real":1,"realp":2.007},{"name":"Pineco","usage":0.38424,"raw":1,"rawp":1.429,"real":1,"realp":2.007},{"name":"Carvanha","usage":0.35266,"raw":5,"rawp":7.143,"real":2,"realp":4.013},{"name":"Drilbur","usage":0.25405,"raw":3,"rawp":4.286,"real":3,"realp":6.02},{"name":"Ditto","usage":0.24007,"raw":2,"rawp":2.857,"real":2,"realp":4.013},{"name":"Koffing","usage":0.24007,"raw":1,"rawp":1.429,"real":1,"realp":2.007},{"name":"Voltorb","usage":0.24007,"raw":2,"rawp":2.857,"real":1,"realp":2.007},{"name":"Unown","usage":0.1197,"raw":2,"rawp":2.857,"real":2,"realp":4.013},{"name":"Jigglypuff","usage":0.1197,"raw":1,"rawp":1.429,"real":1,"realp":2.007},{"name":"Elekid","usage":0.1197,"raw":1,"rawp":1.429,"real":1,"realp":2.007},{"name":"Krabby","usage":0.1197,"raw":1,"rawp":1.429,"real":1,"realp":2.007},{"name":"Anorith","usage":0.02188,"raw":1,"rawp":1.429,"real":1,"realp":2.007},{"name":"Bunnelby","usage":0.02188,"raw":3,"rawp":4.286,"real":3,"realp":6.02},{"name":"Pikipek","usage":0.01398,"raw":1,"rawp":1.429,"real":1,"realp":2.007},{"name":"Dwebble","usage":0.00093,"raw":2,"rawp":2.857,"real":1,"realp":2.007},{"name":"Woobat","usage":0.00093,"raw":3,"rawp":4.286,"real":2,"realp":4.013},{"name":"Pidgeotto","usage":0.0007,"raw":1,"rawp":1.429,"real":0,"realp":0},{"name":"Luvdisc","usage":0.0007,"raw":2,"rawp":2.857,"real":2,"realp":4.013},{"name":"Yamask","usage":0.00014,"raw":2,"rawp":2.857,"real":2,"realp":4.013},{"name":"Kyogre-Primal","usage":0.00014,"raw":3,"rawp":4.286,"real":3,"realp":6.02},{"name":"Swablu","usage":0.00007,"raw":1,"rawp":1.429,"real":1,"realp":2.007},{"name":"Mareanie","usage":0.00007,"raw":3,"rawp":4.286,"real":2,"realp":4.013},{"name":"Spoink","usage":0.00007,"raw":1,"rawp":1.429,"real":1,"realp":2.007},{"name":"Aggron","usage":0,"raw":1,"rawp":1.429,"real":0,"realp":0},{"name":"Marshadow","usage":0,"raw":1,"rawp":1.429,"real":0,"realp":0},{"name":"Beedrill","usage":0,"raw":1,"rawp":1.429,"real":1,"realp":2.007},{"name":"Deoxys-Defense","usage":0,"raw":1,"rawp":1.429,"real":1,"realp":2.007},{"name":"Breloom","usage":0,"raw":1,"rawp":1.429,"real":1,"realp":2.007},{"name":"Porygon-Z","usage":0,"raw":1,"rawp":1.429,"real":1,"realp":2.007},{"name":"Buneary","usage":0,"raw":3,"rawp":4.286,"real":2,"realp":4.013},{"name":"Eevee","usage":0,"raw":2,"rawp":2.857,"real":1,"realp":2.007},{"name":"Hitmonlee","usage":0,"raw":1,"rawp":1.429,"real":0,"realp":0},{"name":"Mimikyu","usage":0,"raw":2,"rawp":2.857,"real":2,"realp":4.013},{"name":"Altaria-Mega","usage":0,"raw":1,"rawp":1.429,"real":1,"realp":2.007},{"name":"Dragonair","usage":0,"raw":1,"rawp":1.429,"real":1,"realp":2.007},{"name":"Diggersby","usage":0,"raw":1,"rawp":1.429,"real":1,"realp":2.007},{"name":"Latias-Mega","usage":0,"raw":1,"rawp":1.429,"real":0,"realp":0},{"name":"Garchomp","usage":0,"raw":1,"rawp":1.429,"real":1,"realp":2.007},{"name":"Milotic","usage":0,"raw":1,"rawp":1.429,"real":1,"realp":2.007},{"name":"Toxapex","usage":0,"raw":1,"rawp":1.429,"real":0,"realp":0},{"name":"Vikavolt","usage":0,"raw":1,"rawp":1.429,"real":1,"realp":2.007},{"name":"Blaziken-Mega","usage":0,"raw":1,"rawp":1.429,"real":1,"realp":2.007},{"name":"Psyduck","usage":0,"raw":1,"rawp":1.429,"real":1,"realp":2.007},{"name":"Arcanine","usage":0,"raw":1,"rawp":1.429,"real":1,"realp":2.007},{"name":"Omastar","usage":0,"raw":1,"rawp":1.429,"real":1,"realp":2.007},{"name":"Shieldon","usage":0,"raw":1,"rawp":1.429,"real":1,"realp":2.007},{"name":"Snorlax","usage":0,"raw":1,"rawp":1.429,"real":1,"realp":2.007},{"name":"Tepig","usage":0,"raw":1,"rawp":1.429,"real":1,"realp":2.007},{"name":"Incineroar","usage":0,"raw":1,"rawp":1.429,"real":1,"realp":2.007},{"name":"Sandshrew-Alola","usage":0,"raw":1,"rawp":1.429,"real":1,"realp":2.007},{"name":"Marill","usage":0,"raw":3,"rawp":4.286,"real":1,"realp":2.007},{"name":"Bulbasaur","usage":0,"raw":1,"rawp":1.429,"real":0,"realp":0},{"name":"Chansey","usage":0,"raw":1,"rawp":1.429,"real":0,"realp":0},{"name":"Celesteela","usage":0,"raw":1,"rawp":1.429,"real":0,"realp":0},{"name":"Xerneas","usage":0,"raw":1,"rawp":1.429,"real":1,"realp":2.007},{"name":"Kabutops","usage":0,"raw":1,"rawp":1.429,"real":0,"realp":0},{"name":"Skiploom","usage":0,"raw":1,"rawp":1.429,"real":1,"realp":2.007},{"name":"Sylveon","usage":0,"raw":1,"rawp":1.429,"real":0,"realp":0},{"name":"Stufful","usage":0,"raw":2,"rawp":2.857,"real":0,"realp":0},{"name":"Charizard-Mega-X","usage":0,"raw":1,"rawp":1.429,"real":1,"realp":2.007},{"name":"Charizard-Mega-Y","usage":0,"raw":1,"rawp":1.429,"real":0,"realp":0},{"name":"Jolteon","usage":0,"raw":2,"rawp":2.857,"real":2,"realp":4.013},{"name":"Slaking","usage":0,"raw":1,"rawp":1.429,"real":1,"realp":2.007},{"name":"Rotom-Wash","usage":0,"raw":1,"rawp":1.429,"real":1,"realp":2.007},{"name":"Avalugg","usage":0,"raw":1,"rawp":1.429,"real":1,"realp":2.007},{"name":"Ekans","usage":0,"raw":3,"rawp":4.286,"real":3,"realp":6.02},{"name":"Litten","usage":0,"raw":4,"rawp":5.714,"real":2,"realp":4.013},{"name":"Zygarde","usage":0,"raw":1,"rawp":1.429,"real":0,"realp":0},{"name":"Dragonite","usage":0,"raw":1,"rawp":1.429,"real":1,"realp":2.007},{"name":"Axew","usage":0,"raw":1,"rawp":1.429,"real":1,"realp":2.007},{"name":"Ursaring","usage":0,"raw":1,"rawp":1.429,"real":1,"realp":2.007},{"name":"Ivysaur","usage":0,"raw":1,"rawp":1.429,"real":0,"realp":0},{"name":"Drifblim","usage":0,"raw":1,"rawp":1.429,"real":1,"realp":2.007},{"name":"Audino","usage":0,"raw":1,"rawp":1.429,"real":1,"realp":2.007},{"name":"Fennekin","usage":0,"raw":1,"rawp":1.429,"real":0,"realp":0},{"name":"Drifloon","usage":0,"raw":1,"rawp":1.429,"real":1,"realp":2.007},{"name":"Kirlia","usage":0,"raw":3,"rawp":4.286,"real":2,"realp":4.013},{"name":"Mewtwo-Mega-Y","usage":0,"raw":1,"rawp":1.429,"real":1,"realp":2.007},{"name":"Greninja-Ash","usage":0,"raw":2,"rawp":2.857,"real":2,"realp":4.013},{"name":"Gengar","usage":0,"raw":1,"rawp":1.429,"real":1,"realp":2.007},{"name":"Pancham","usage":0,"raw":1,"rawp":1.429,"real":1,"realp":2.007},{"name":"Bronzor","usage":0,"raw":3,"rawp":4.286,"real":2,"realp":4.013},{"name":"Typhlosion","usage":0,"raw":1,"rawp":1.429,"real":1,"realp":2.007},{"name":"Ho-Oh","usage":0,"raw":1,"rawp":1.429,"real":1,"realp":2.007},{"name":"Rayquaza-Mega","usage":0,"raw":1,"rawp":1.429,"real":1,"realp":2.007},{"name":"Sceptile-Mega","usage":0,"raw":1,"rawp":1.429,"real":1,"realp":2.007},{"name":"Lucario-Mega","usage":0,"raw":1,"rawp":1.429,"real":1,"realp":2.007},{"name":"Cutiefly","usage":0,"raw":1,"rawp":1.429,"real":1,"realp":2.007},{"name":"Charmander","usage":0,"raw":1,"rawp":1.429,"real":0,"realp":0},{"name":"Elgyem","usage":0,"raw":1,"rawp":1.429,"real":0,"realp":0},{"name":"Sableye-Mega","usage":0,"raw":2,"rawp":2.857,"real":2,"realp":4.013},{"name":"Natu","usage":0,"raw":3,"rawp":4.286,"real":3,"realp":6.02},{"name":"Volcanion","usage":0,"raw":1,"rawp":1.429,"real":1,"realp":2.007},{"name":"Aegislash","usage":0,"raw":1,"rawp":1.429,"real":1,"realp":2.007},{"name":"Scraggy","usage":0,"raw":3,"rawp":4.286,"real":1,"realp":2.007},{"name":"Samurott","usage":0,"raw":1,"rawp":1.429,"real":1,"realp":2.007},{"name":"Zoroark","usage":0,"raw":1,"rawp":1.429,"real":0,"realp":0},{"name":"Cacnea","usage":0,"raw":2,"rawp":2.857,"real":2,"realp":4.013},{"name":"Nuzleaf","usage":0,"raw":1,"rawp":1.429,"real":1,"realp":2.007},{"name":"Cyndaquil","usage":0,"raw":1,"rawp":1.429,"real":0,"realp":0},{"name":"Torchic","usage":0,"raw":2,"rawp":2.857,"real":1,"realp":2.007},{"name":"Phanpy","usage":0,"raw":1,"rawp":1.429,"real":1,"realp":2.007},{"name":"Mudbray","usage":0,"raw":1,"rawp":1.429,"real":1,"realp":2.007},{"name":"Hydreigon","usage":0,"raw":1,"rawp":1.429,"real":1,"realp":2.007},{"name":"Golisopod","usage":0,"raw":1,"rawp":1.429,"real":1,"realp":2.007},{"name":"Shedinja","usage":0,"raw":1,"rawp":1.429,"real":0,"realp":0},{"name":"Forretress","usage":0,"raw":2,"rawp":2.857,"real":1,"realp":2.007},{"name":"Gallade","usage":0,"raw":1,"rawp":1.429,"real":1,"realp":2.007},{"name":"Salamence-Mega","usage":0,"raw":1,"rawp":1.429,"real":1,"realp":2.007}]}